Workbook
Name adhesion: #REF!

Sheet Perfil da Organização
B2: Lei Geral de Proteção de Dados (LGPD)
B5: Perfil da Organização
B6: Nome: | D6: Empresa Beta | G6: DPO (Data Protection Officer)
B7: Lucro anual estimado | G7: Não
B8: Setor de Atuação | G8: Estrutura Organizacional do DPO (Papéis estabelecidos)
B9: Região(ões) de operação: | G9: Não
B10: Controlador ou Operador | G10: Quais dos processos abaixo estão implementados ?
B11: Orçamento de proteção de dados para os próximos 12 meses? | G11: N | H11: Privacy by Design | I11: N | J11: Gestão de incidentes de privacidade
G12: N | H12: DPIA (Data Protection & Impact Assessment) | I12: S | J12: Descrição de bases legais para legitimação
B13: Existem outros departamentos com orçamento de proteção de dados? | G13: N | H13: Processo para gestão de petição de titulares | I13: N | J13: Descrição de períodos de retenção dos dados pessoais
G14: N | H14: Políticas e normas de privacidade | I14: N | J14: Segurança da Informação e Criptografia
B15: Orçamento anual | G15: Principais stakeholders
B16: Total
B17: Investimento
B18: Despesas operacionais
B20: Obs: Alguns campos não precisam ser preenchidos em caso de Instituições Públicas | H20: Ex.: Lucro estimado

Sheet Aplicabilidade
B2: Aplicabilidade
B5: Art. 3º Esta Lei aplica-se a qualquer operação de tratamento realizada por pessoa natural ou por pessoa jurídica de direito público ou privado, independentemente do meio, do país de sua sede ou do país onde estejam localizados os dados, desde que:
B6: I – a operação de tratamento seja realizada no território nacional; II – a atividade de tratamento tenha por objetivo a oferta ou o fornecimento de bens ou serviços ou o tratamento de dados de indivíduos localizados no território nacional; III – os dados pessoais objeto do tratamento tenham sido coletados no território nacional. § 1º Consideram-se coletados no território nacional os dados pessoais cujo titular nele se encontre no momento da coleta. § 2º Excetua-se do disposto no inciso I deste artigo o tratamento de dados previsto no inciso III do caput do art. 4º desta Lei.
B8: Art. 4º Esta Lei não se aplica ao tratamento de dados pessoais:
B9: I – realizado por pessoa natural para fins exclusivamente particulares e não econômicos;
B10: II – realizado para fins exclusivamente:
B11: a) jornalísticos;
B12: b) artísticos;
B13: c) acadêmicos, aplicando-se a esta hipótese os arts. 13 e 17 desta Lei;
B14: d) de segurança pública;
B15: e) de defesa nacional;
B16: f) de segurança do Estado;
... B20: b) sejam objeto de transferência internacional de dados com outro país que não o de proveniência, desde que o país de proveniência proporcione grau de proteção de dados pessoais adequado ao previsto nesta Lei.

Sheet Conceitos
B2: Conceitos
B4: Conceitos adotados pela Lei Geral de Proteção de Dados conforme o Artigo 5 da LGPD:
B5: Dado Pessoal
B6: Informação relacionada à pessoa natural identificada ou identificável
B8: Dado Pessoal Sensível
B9: Dado pessoal sobre origem racial ou étnica, convicção religiosa, opinião política, filiação a sindicato ou a organização de caráter religioso, filosófico ou político, saúde, vida sexual, genética ou biometria, quando vinculado a pessoa natural
B11: Banco de Dados
B12: Conjunto estruturado de dados pessoais, estabelecido em um ou em vários locais, em suporte eletrônico ou físico
B14: Dado Anonimizado
B15: Dado relativo a titular que não possa ser identificado, utilizando-se meios técnicos razoáveis e disponíveis na ocasião de seu tratamento
B17: Titular
B18: A pessoa natural a quem se referem os dados pessoais que são objeto de tratamento
... B60: Documentação do responsável que contém a descrição dos processos de tratamento de dados pessoais que podem gerar riscos às liberdades civis e aos direitos fundamentais, bem como medidas, salvaguardas e mecanismos de mitigação de risco

Sheet Controles
B2: Matriz de Controles e Avaliação de Gaps
B5: Controle | C5: Domínio | D5: Instruções | E5: Questionamentos | F5: Artigo | G5: Capítulo | H5: Cenário Atual | I5: Mapeamento | J5: Aderência | K5: Ponto de Melhoria
B7: 1 | C7: Tratamento dos dados pessoais | D7: Descrever | E7: Quais as principais atividades de tratamento de dados pessoais realizadas pela organização e, em linhas gerais, como tais atividades são realizadas? | F7: Art. 5º Para os fins desta Lei, considera-se: I - dado pessoal: informação relacionada a pessoa natural identificada ou identificável; X - tratamento: toda operação realizada com dados pessoais, como as que se referem a coleta, produção, recepção, classificação, utilização, acesso, reprodução, transmissão, distribuição, processamento, arquivamento, armazenamento, eliminação, avaliação ou controle da informação, modificação, comunicação, transferência, difusão ou extração. | G7: CAPÍTULO I - DISPOSIÇÕES PRELIMINARES | H7: A Empresa Beta realiza o tratamento de dados para prestação de serviços aos seus clientes, bem como para gestão interna de seus colaboradores. | I7: Em andamento | J7: Parcialmente aderente | K7: Adequar o tratamento de dados pessoais as diretrizes da LGPD (definição das bases legais)
B8: 2 | C8: Tratamento dos dados pessoais sensíveis | D8: S/N | E8: A organização realiza algum tipo de tratamento de dado pessoal sensível? | F8: Art. 5º Para os fins desta Lei, considera-se: II - dado pessoal sensível: dado pessoal sobre origem racial ou étnica, convicção religiosa, opinião política, filiação a sindicato ou a organização de caráter religioso, filosófico ou político, dado referente à saúde ou à vida sexual, dado genético ou biométrico, quando vinculado a uma pessoa natural; X - tratamento: toda operação realizada com dados pessoais, como as que se referem a coleta, produção, recepção, classificação, utilização, acesso, reprodução, transmissão, distribuição, processamento, arquivamento, armazenamento, eliminação, avaliação ou controle da informação, modificação, comunicação, transferência, difusão ou extração. | G8: CAPÍTULO I - DISPOSIÇÕES PRELIMINARES | H8: Sim | I8: Em andamento | J8: Parcialmente aderente | K8: Adequar o tratamento de dados pessoais sensíveis as diretrizes da LGPD (definição das bases legais)
B9: 3 | C9: Tratamento dos dados pessoais sensíveis | D9: Se a pergunta anterior for Sim | E9: Quais as principais atividades de tratamento de dados pessoais sensíveis realizadas pela organização e, em linhas gerais, como tais atividades são realizadas? | F9: Art. 5º Para os fins desta Lei, considera-se: II - dado pessoal sensível: dado pessoal sobre origem racial ou étnica, convicção religiosa, opinião política, filiação a sindicato ou a organização de caráter religioso, filosófico ou político, dado referente à saúde ou à vida sexual, dado genético ou biométrico, quando vinculado a uma pessoa natural; X - tratamento: toda operação realizada com dados pessoais, como as que se referem a coleta, produção, recepção, classificação, utilização, acesso, reprodução, transmissão, distribuição, processamento, arquivamento, armazenamento, eliminação, avaliação ou controle da informação, modificação, comunicação, transferência, difusão ou extração. | G9: CAPÍTULO I - DISPOSIÇÕES PRELIMINARES | H9: São tratados dados pessoais sensíveis para a diversidade na empresa e uso de imagem de colaboradores. | I9: Em andamento | J9: Parcialmente aderente | K9: Adequar o tratamento de dados pessoais sensíveis as diretrizes da LGPD (definição das bases legais)
B10: 4 | C10: Tratamento dos dados pessoais | D10: S/N | E10: As operações de tratamento de dados pessoais são realizadas com base na boa fé e em algum dos princípios de privacidade listados abaixo? | F10: Art. 6º As atividades de tratamento de dados pessoais deverão observar a boa-fé e os seguintes princípios: I – finalidade: realização do tratamento para propósitos legítimos, específicos, explícitos e informados ao titular, sem possibilidade de tratamento posterior de forma incompatível com esses propósitos; II – adequação: compatibilidade do tratamento com as finalidades informadas ao titular, de acordo com o contexto do tratamento; III – necessidade: limitação do tratamento ao mínimo necessário para a realização de suas finalidades, com a utilização de dados pertinentes, proporcionais e não excessivos em relação às finalidades do tratamento; IV – livre acesso: garantia, aos titulares, de consulta facilitada e gratuita sobre a forma e a duração do tratamento, bem como sobre a integralidade de seus dados pessoais; V – qualidade dos dados: garantia, aos titulares, de exatidão, clareza, relevância e atualização dos dados, de acordo com a necessidade e para o cumprimento da finalidade de seu tratamento; VI – transparência: garantia, aos titulares, de informações claras, precisas e facilmente acessíveis sobre a realização do tratamento e os respectivos agentes de tratamento, observados os segredos comercial e industrial; VII – segurança: utilização de medidas técnicas e administrativas aptas a proteger os dados pessoais de acessos não autorizados e de eventos acidentais ou ilícitos de destruição, perda, alteração, comunicação ou difusão; VIII – prevenção: adoção de medidas para prevenir a ocorrência de danos em virtude do tratamento de dados pessoais; IX – não discriminação: impossibilidade de realização do tratamento para fins discriminatórios ilícitos ou abusivos; X – responsabilização e prestação de contas: demonstração, pelo agente, da adoção de medidas eficazes e capazes de comprovar a observância e o cumprimento das normas de proteção de dados pessoais e, inclusive, da eficácia dessas medidas. | G10: CAPÍTULO I - DISPOSIÇÕES PRELIMINARES | H10: Parcialmente.
D11: Checkbox | E11: I – finalidade: realização do tratamento para propósitos legítimos, específicos, explícitos e informados ao titular, sem possibilidade de tratamento posterior de forma incompatível com esses propósitos; | I11: Em andamento | J11: Parcialmente aderente | K11: Revisão de Políticas para conformidade com o príncipio.
E12: II – adequação: compatibilidade do tratamento com as finalidades informadas ao titular, de acordo com o contexto do tratamento; | I12: Em andamento | J12: Parcialmente aderente | K12: Revisão de Políticas para conformidade com o príncipio.
E13: III – necessidade: limitação do tratamento ao mínimo necessário para a realização de suas finalidades, com a utilização de dados pertinentes, proporcionais e não excessivos em relação às finalidades do tratamento; | I13: Em andamento | J13: Parcialmente aderente | K13: Revisão de Políticas para conformidade com o príncipio.
E14: IV – livre acesso: garantia, aos titulares, de consulta facilitada e gratuita sobre a forma e a duração do tratamento, bem como sobre a integralidade de seus dados pessoais; | I14: Em andamento | J14: Parcialmente aderente | K14: Indicação de um canal de contato para possibilitar ao titular exercer os seus direitos
E15: V – qualidade dos dados: garantia, aos titulares, de exatidão, clareza, relevância e atualização dos dados, de acordo com a necessidade e para o cumprimento da finalidade de seu tratamento; | I15: Em andamento | J15: Parcialmente aderente | K15: Indicação de um canal de contato para possibilitar ao titular exercer os seus direitos
E16: VI – transparência: garantia, aos titulares, de informações claras, precisas e facilmente acessíveis sobre a realização do tratamento e os respectivos agentes de tratamento, observados os segredos comercial e industrial; | I16: Em andamento | J16: Parcialmente aderente | K16: Revisão de Políticas para conformidade com o príncipio.
E17: VII – segurança: utilização de medidas técnicas e administrativas aptas a proteger os dados pessoais de acessos não autorizados e de eventos acidentais ou ilícitos de destruição, perda, alteração, comunicação ou difusão; | I17: Em andamento | J17: Parcialmente aderente | K17: Necessário adequar as Políticas internas e externas e os processos de Tratamento de Dados Pessoais da Empresa Beta para atender aos príncipios da LGPD.
E18: VIII – prevenção: adoção de medidas para prevenir a ocorrência de danos em virtude do tratamento de dados pessoais; | I18: Em andamento | J18: Parcialmente aderente | K18: Necessário adequar as Políticas internas e externas e os processos de Tratamento de Dados Pessoais da Empresa Beta para atender aos príncipios da LGPD.
E19: IX – não discriminação: impossibilidade de realização do tratamento para fins discriminatórios ilícitos ou abusivos; | I19: Em andamento | J19: Não aderente | K19: Avaliar a questão de realização de background chack pela Empresa Beta para contratacão de novos colaboradores.
E20: X – responsabilização e prestação de contas: demonstração, pelo agente, da adoção de medidas eficazes e capazes de comprovar a observância e o cumprimento das normas de proteção de dados pessoais e, inclusive, da eficácia dessas medidas. | I20: Em andamento | J20: Não aderente | K20: A Empresa Beta deverá demonstrar por meio de politicas, listas de realização de treinamentos, e outros documentos que está em processo de adequação à LGPD.
B21: 5 | C21: Privacy By Design | D21: S/N | E21: A organização possui um processo de Privacy by Design? | F21: Art. 6º As atividades de tratamento de dados pessoais deverão observar a boa-fé e os seguintes princípios: I – finalidade: realização do tratamento para propósitos legítimos, específicos, explícitos e informados ao titular, sem possibilidade de tratamento posterior de forma incompatível com esses propósitos; II – adequação: compatibilidade do tratamento com as finalidades informadas ao titular, de acordo com o contexto do tratamento; III – necessidade: limitação do tratamento ao mínimo necessário para a realização de suas finalidades, com a utilização de dados pertinentes, proporcionais e não excessivos em relação às finalidades do tratamento; IV – livre acesso: garantia, aos titulares, de consulta facilitada e gratuita sobre a forma e a duração do tratamento, bem como sobre a integralidade de seus dados pessoais; V – qualidade dos dados: garantia, aos titulares, de exatidão, clareza, relevância e atualização dos dados, de acordo com a necessidade e para o cumprimento da finalidade de seu tratamento; VI – transparência: garantia, aos titulares, de informações claras, precisas e facilmente acessíveis sobre a realização do tratamento e os respectivos agentes de tratamento, observados os segredos comercial e industrial; VII – segurança: utilização de medidas técnicas e administrativas aptas a proteger os dados pessoais de acessos não autorizados e de eventos acidentais ou ilícitos de destruição, perda, alteração, comunicação ou difusão; VIII – prevenção: adoção de medidas para prevenir a ocorrência de danos em virtude do tratamento de dados pessoais; IX – não discriminação: impossibilidade de realização do tratamento para fins discriminatórios ilícitos ou abusivos; X – responsabilização e prestação de contas: demonstração, pelo agente, da adoção de medidas eficazes e capazes de comprovar a observância e o cumprimento das normas de proteção de dados pessoais e, inclusive, da eficácia dessas medidas. | G21: CAPÍTULO I - DISPOSIÇÕES PRELIMINARES | H21: Não. | I21: Não iniciado | J21: Não aderente | K21: Ao desenvolver um novo produto ou serviço a Empresa Beta deverá avaliar as diretrizes da LGPD, realizando o processo de Privacy by Design.
D22: Se a pergunta anterior for Sim S/N | E22: O processo de Privacy by Design considera o princípio da boa-fé e os 10 princípios de privacidade? | F22: Art. 6º As atividades de tratamento de dados pessoais deverão observar a boa-fé e os seguintes princípios: I – finalidade: realização do tratamento para propósitos legítimos, específicos, explícitos e informados ao titular, sem possibilidade de tratamento posterior de forma incompatível com esses propósitos; II – adequação: compatibilidade do tratamento com as finalidades informadas ao titular, de acordo com o contexto do tratamento; III – necessidade: limitação do tratamento ao mínimo necessário para a realização de suas finalidades, com a utilização de dados pertinentes, proporcionais e não excessivos em relação às finalidades do tratamento; IV – livre acesso: garantia, aos titulares, de consulta facilitada e gratuita sobre a forma e a duração do tratamento, bem como sobre a integralidade de seus dados pessoais; V – qualidade dos dados: garantia, aos titulares, de exatidão, clareza, relevância e atualização dos dados, de acordo com a necessidade e para o cumprimento da finalidade de seu tratamento; VI – transparência: garantia, aos titulares, de informações claras, precisas e facilmente acessíveis sobre a realização do tratamento e os respectivos agentes de tratamento, observados os segredos comercial e industrial; VII – segurança: utilização de medidas técnicas e administrativas aptas a proteger os dados pessoais de acessos não autorizados e de eventos acidentais ou ilícitos de destruição, perda, alteração, comunicação ou difusão; VIII – prevenção: adoção de medidas para prevenir a ocorrência de danos em virtude do tratamento de dados pessoais; IX – não discriminação: impossibilidade de realização do tratamento para fins discriminatórios ilícitos ou abusivos; X – responsabilização e prestação de contas: demonstração, pelo agente, da adoção de medidas eficazes e capazes de comprovar a observância e o cumprimento das normas de proteção de dados pessoais e, inclusive, da eficácia dessas medidas. | G22: CAPÍTULO I - DISPOSIÇÕES PRELIMINARES | H22: Não existe. | I22: Não iniciado | J22: Não aderente | K22: N/A
D23: Se a pergunta principal for Sim S/N | E23: O processo de Privacy by Design está documentado ? | F23: Art. 6º As atividades de tratamento de dados pessoais deverão observar a boa-fé e os seguintes princípios: I - finalidade: realização do tratamento para propósitos legítimos, específicos, explícitos e informados ao titular, sem possibilidade de tratamento posterior de forma incompatível com essas finalidades; II - adequação: compatibilidade do tratamento com as finalidades informadas ao titular, de acordo com o contexto do tratamento; III - necessidade: limitação do tratamento ao mínimo necessário para a realização de suas finalidades, com abrangência dos dados pertinentes, proporcionais e não excessivos em relação às finalidades do tratamento de dados; IV - livre acesso: garantia, aos titulares, de consulta facilitada e gratuita sobre a forma e a duração do tratamento, bem como sobre a integralidade de seus dados pessoais; V - qualidade dos dados: garantia, aos titulares, de exatidão, clareza, relevância e atualização dos dados, de acordo com a necessidade e para o cumprimento da finalidade de seu tratamento; VI - transparência: garantia, aos titulares, de informações claras, precisas e facilmente acessíveis sobre a realização do tratamento e os respectivos agentes de tratamento, observados os segredos comercial e industrial; VII - segurança: utilização de medidas técnicas e administrativas aptas a proteger os dados pessoais de acessos não autorizados e de situações acidentais ou ilícitas de destruição, perda, alteração, comunicação ou difusão; VIII - prevenção: adoção de medidas para prevenir a ocorrência de danos em virtude do tratamento de dados pessoais; IX - não discriminação: impossibilidade de realização do tratamento para fins discriminatórios ilícitos ou abusivos; X - responsabilização e prestação de contas: demonstração, pelo agente, da adoção de medidas eficazes e capazes de comprovar a observância e o cumprimento das normas de proteção de dados pessoais e, inclusive, da eficácia dessas medidas. | G23: CAPÍTULO I - DISPOSIÇÕES PRELIMINARES | H23: Não existe. | I23: Não iniciado | J23: Não aderente | K23: N/A
B24: 6 | C24: DPIA | D24: S/N | E24: A organização emite atualmente algum tipo de relatório de impacto de proteção de dados pessoais - DPIA (Data Protection & Impact Assessment)? | F24: Art. 38. A autoridade nacional poderá determinar ao controlador que elabore relatório de impacto à proteção de dados pessoais, inclusive de dados sensíveis, referente a suas operações de tratamento de dados, nos termos de regulamento, observados os segredos comercial e industrial. Parágrafo único. Observado o disposto no caput deste artigo, o relatório deverá conter, no mínimo, a descrição dos tipos de dados coletados, a metodologia utilizada para a coleta e para a garantia da segurança das informações e a análise do controlador com relação a medidas, salvaguardas e mecanismos de mitigação de risco adotados. | G24: CAPÍTULO VI DOS AGENTES DE TRATAMENTO DE DADOS PESSOAIS Seção I Do Controlador e do Operador | H24: Não | I24: Não iniciado | J24: Não aderente | K24: Ao utilizar a base legal do legitimo interesse ou em casos que possam gerar risco ao titular, ou ainda quando solicitado pela ANPD a Empresa Beta deverá elaborar o Relatório de Impacto.
D25: Se a pergunta anterior for Sim S/N | E25: O processo de DPIA (Data Protection & Impact Assessment) considera o princípio da boa fé e os 10 princípios de privacidade ? | F25: Art. 6º As atividades de tratamento de dados pessoais deverão observar a boa-fé e os seguintes princípios: I - finalidade: realização do tratamento para propósitos legítimos, específicos, explícitos e informados ao titular, sem possibilidade de tratamento posterior de forma incompatível com essas finalidades; II - adequação: compatibilidade do tratamento com as finalidades informadas ao titular, de acordo com o contexto do tratamento; III - necessidade: limitação do tratamento ao mínimo necessário para a realização de suas finalidades, com abrangência dos dados pertinentes, proporcionais e não excessivos em relação às finalidades do tratamento de dados; IV - livre acesso: garantia, aos titulares, de consulta facilitada e gratuita sobre a forma e a duração do tratamento, bem como sobre a integralidade de seus dados pessoais; V - qualidade dos dados: garantia, aos titulares, de exatidão, clareza, relevância e atualização dos dados, de acordo com a necessidade e para o cumprimento da finalidade de seu tratamento; VI - transparência: garantia, aos titulares, de informações claras, precisas e facilmente acessíveis sobre a realização do tratamento e os respectivos agentes de tratamento, observados os segredos comercial e industrial; VII - segurança: utilização de medidas técnicas e administrativas aptas a proteger os dados pessoais de acessos não autorizados e de situações acidentais ou ilícitas de destruição, perda, alteração, comunicação ou difusão; VIII - prevenção: adoção de medidas para prevenir a ocorrência de danos em virtude do tratamento de dados pessoais; IX - não discriminação: impossibilidade de realização do tratamento para fins discriminatórios ilícitos ou abusivos; X - responsabilização e prestação de contas: demonstração, pelo agente, da adoção de medidas eficazes e capazes de comprovar a observância e o cumprimento das normas de proteção de dados pessoais e, inclusive, da eficácia dessas medidas. | G25: CAPÍTULO I - DISPOSIÇÕES PRELIMINARES | H25: Não existe. | I25: Não iniciado | J25: Não aderente | K25: N/A
D26: Se a pergunta principal for Sim | E26: O processo de DPIA está documentado? Com qual frequência o processo é conduzido? Para qual escopo ? | F26: Art. 38. A autoridade nacional poderá determinar ao controlador que elabore relatório de impacto à proteção de dados pessoais, inclusive de dados sensíveis, referente a suas operações de tratamento de dados, nos termos de regulamento, observados os segredos comercial e industrial. Parágrafo único. Observado o disposto no caput deste artigo, o relatório deverá conter, no mínimo, a descrição dos tipos de dados coletados, a metodologia utilizada para a coleta e para a garantia da segurança das informações e a análise do controlador com relação a medidas, salvaguardas e mecanismos de mitigação de risco adotados. | G26: CAPÍTULO VI DOS AGENTES DE TRATAMENTO DE DADOS PESSOAIS Seção I Do Controlador e do Operador | H26: Não existe. | I26: Não iniciado | J26: Não aderente | K26: N/A
D27: S/N | E27: Um relatório de impacto a proteção dos dados foi gerado para os casos em que o legítimo interesse foi adotado como base legal ? | F27: Art 10 § 3º A autoridade nacional poderá solicitar ao controlador relatório de impacto à proteção de dados pessoais, quando o tratamento tiver como fundamento seu interesse legítimo, observados os segredos comercial e industrial. | G27: CAPÍTULO II - DO TRATAMENTO DE DADO S PESSOAIS Seção I Dos Requisitos para o Tratamen to de Dados Pessoais | H27: Não foi elaborado nenhum Relatório de Impacto | I27: Não iniciado | J27: Não aderente | K27: N/A
B28: 7 | C28: Direito dos titulares dos dados | D28: S/N | E28: Existe um processo/sistema que permite o atendimento às requisições do titular (acesso, confirmação, correção,anonimização,bloqueio,eliminação,portabilidade e revogação de consentimento)? | F28: Art. 18. O titular dos dados pessoais tem direito a obter do controlador, em relação aos dados do titular por ele tratados, a qualquer momento e mediante requisição: I - confirmação da existência de tratamento; II - acesso aos dados; III - correção de dados incompletos, inexatos ou desatualizados; IV - anonimização, bloqueio ou eliminação de dados desnecessários, excessivos ou tratados em desconformidade com o disposto nesta Lei; V - portabilidade dos dados a outro fornecedor de serviço ou produto, mediante requisição expressa e observados os segredos comercial e industrial, de acordo com a regulamentação do órgão controlador; VI - eliminação dos dados pessoais tratados com o consentimento do titular, exceto nas hipóteses previstas no art. 16 desta Lei; VII - informação das entidades públicas e privadas com as quais o controlador realizou uso compartilhado de dados; VIII - informação sobre a possibilidade de não fornecer consentimento e sobre as consequências da negativa; IX - revogação do consentimento, nos termos do § 5º do art. 8º desta Lei. | G28: CAPÍTULO III DOS DIREITOS DO TI TULAR | H28: Inexiste procedimento para atendimento aos Titulares. | I28: Não iniciado | J28: Não aderente | K28: É necessário estabelecer um procedimento para atendimento das demandas dos titulares.
D29: Se a pergunta anterior for Sim S/N | E29: O processo/sistema permite que o titular tenha acesso facilitado às informações sobre o tratamento de seus dados (finalidade, forma, duração do tratamento, dados do controlador, uso compartilhado, responsabilidade e demais direitos do titular) de forma clara e simplificada? | F29: Art. 9º O titular tem direito ao acesso facilitado às informações sobre o tratamento de seus dados, que deverão ser disponibilizadas de forma clara, adequada e ostensiva acerca de, entre outras características previstas em regulamentação para o atendimento do princípio do livre acesso: I - finalidade específica do tratamento; II - forma e duração do tratamento, observados os segredos comercial e industrial; III - identificação do controlador; IV - informações de contato do controlador; V - informações acerca do uso compartilhado de dados pelo controlador e a finalidade; VI - responsabilidades dos agentes que realizarão o tratamento; e VII - direitos do titular, com menção explícita aos direitos contidos no art. 18 desta Lei. | G29: CAPÍTULO II - DO TRATAMENTO DE DADOS PESSOAIS - Seção I Dos Requisitos para o Tratamento de Dados Pessoais | H29: Inexiste procedimento para atendimento aos Titulares. | I29: Não iniciado | J29: Não aderente | K29: É necessário estabelecer um procedimento para atendimento das demandas dos titulares.
D30: S/N | E30: Existe um prazo para resposta às requisições dos titulares relacionadas à existênia ou acesso a seus dados pessoais? | F30: Art. 19. A confirmação de existência ou o acesso a dados pessoais serão providenciados, mediante requisição do titular: I - em formato simplificado, imediatamente; ou II - por meio de declaração clara e completa, que indique a origem dos dados, a inexistência de registro, os critérios utilizados e a finalidade do tratamento, observados os segredos comercial e industrial, fornecida no prazo de até 15 (quinze) dias, contado da data do requerimento do titular. § 1º Os dados pessoais serão armazenados em formato que favoreça o exercício do direito de acesso. § 2º As informações e os dados poderão ser fornecidos, a critério do titular: I - por meio eletrônico, seguro e idôneo para esse fim; ou II - sob forma impressa. | G30: CAPÍTULO III - DOS DIREITOS DO TITULAR | H30: Inexiste procedimento para resposta aos Titulares. | I30: Não iniciado | J30: Não aderente | K30: Elaboração de procedimento para atender as demandas do colaborador, inclusive com indicação de prazo de resposta.
D31: S/N | E31: Existe um procedimento padrão para atendimento às requisições dos titulares caso o atendimento não possa ser realizado de forma imediata? | F31: Art. 18 § 4º Em caso de impossibilidade de adoção imediata da providência de que trata o § 3º deste artigo, o controlador enviará ao titular resposta em que poderá: I - comunicar que não é agente de tratamento dos dados e indicar, sempre que possível, o agente; ou II - indicar as razões de fato ou de direito que impedem a adoção imediata da providência | G31: CAPÍTULO III - DOS DIREITOS DO TITULAR | H31: Inexiste procedimento para atendimento aos Titulares. | I31: Não iniciado | J31: Não aderente | K31: Definir um canal e um processo para atender as demandas do titular de dados.
D32: S/N | E32: O processo de correção, eliminação, anonimização e bloqueio de dados, originado da requisição de um titular, foi desenhado de modo a acionar todas as empresas com as quais os dados do titular foram compartilhados? | F32: Art. 18. § 6º O responsável deverá informar de maneira imediata aos agentes de tratamento com os quais tenha realizado uso compartilhado de dados a correção, a eliminação, a anonimização ou o bloqueio dos dados, para que repitam idêntico procedimento. | G32: CAPÍTULO III - DOS DIREITOS DO TITULAR | H32: Inexiste procedimento para atendimento aos Titulares. | I32: Não iniciado | J32: Não aderente | K32: Definir um canal e um processo para atender as demandas do titular de dados.
D33: S/N | E33: Existem decisões tomadas com base em tratamentos automatizados? | F33: Art. 20. O titular dos dados tem direito a solicitar revisão, por pessoa natural, de decisões tomadas unicamente com base em tratamento automatizado de dados pessoais que afetem seus interesses, inclusive de decisões destinadas a definir o seu perfil pessoal, profissional, de consumo e de crédito ou os aspectos de sua personalidade. § 1º O controlador deverá fornecer, sempre que solicitadas, informações claras e adequadas a respeito dos critérios e dos procedimentos utilizados para a decisão automatizada, observados os segredos comercial e industrial. | G33: CAPÍTULO III - DOS DIREITOS DO TITULAR | H33: Não | I33: Não iniciado | J33: Não aderente | K33: N/A
B34: 8 | C34: Tratamento dos dados pessoais - Legitimação de uso de dados | D34: S/N | E34: A organização possui um inventário de dados pessoais com a indicação das respectivas bases legais (justificativas) para legitimação do uso dos dados? | F34: Art. 7º O tratamento de dados pessoais somente poderá ser realizado nas seguintes hipóteses: I - mediante o fornecimento de consentimento pelo titular; II - para o cumprimento de obrigação legal ou regulatória pelo controlador; III - pela administração pública, para o tratamento e uso compartilhado de dados necessários à execução de políticas públicas previstas em leis e regulamentos ou respaldadas em contratos, convênios ou instrumentos congêneres, observadas as disposições do Capítulo IV desta Lei; IV - para a realização de estudos por órgão de pesquisa, garantida, sempre que possível, a anonimização dos dados pessoais; V - quando necessário para a execução de contrato ou de procedimentos preliminares relacionados a contrato do qual seja parte o titular, a pedido do titular dos dados; VI - para o exercício regular de direitos em processo judicial, administrativo ou arbitral, esse último nos termos da Lei nº 9.307, de 23 de setembro de 1996 (Lei de Arbitragem); VII - para a proteção da vida ou da incolumidade física do titular ou de terceiro; VIII - para a tutela da saúde, em procedimento realizado por profissionais da área da saúde ou por entidades sanitárias; IX - quando necessário para atender aos interesses legítimos do controlador ou de terceiro, exceto no caso de prevalecerem direitos e liberdades fundamentais do titular que exijam a proteção dos dados pessoais; ou X - para a proteção do crédito, inclusive quanto ao disposto na legislação pertinente. § 1º Nos casos de aplicação do disposto nos incisos II e III do caput deste artigo e excetuadas as hipóteses previstas no art. 4º desta Lei, o titular será informado das hipóteses em que será admitido o tratamento de seus dados. § 2º A forma de disponibilização das informações previstas no § 1º e no inciso I do caput do art. 23 desta Lei poderá ser especificada pela autoridade nacional. | G34: CAPÍTULO II - DO TRATAMENTO DE DADO S PESSOAIS Seção I Dos Requisitos para o Tratamen to de Dados Pessoais | H34: O Mapeamento de Dados está em processo de finalização. | I34: Em andamento | J34: Parcialmente aderente | K34: O mapeamento de dados é um documento extremamente importante para a Empresa Beta e a avaliação do ciclo de dados permite a adequação à LGPD em conformidade com o que prevê a Lei.
B35: 9 | C35: Contratos | D35: S/N | E35: Os contratos celebrados pela organização com clientes, fornecedores, empregados, prestadores de serviço, etc, possuem cláusula relativa ao tratamento de dados pessoais se e quando aplicável? | F35: Art. 7º O tratamento de dados pessoais somente poderá ser realizado nas seguintes hipóteses: V - quando necessário para a execução de contrato ou de procedimentos preliminares relacionados a contrato do qual seja parte o titular, a pedido do titular dos dados. | G35: CAPÍTULO II - DO TRATAMENTO DE DADO S PESSOAIS Seção I Dos Requisitos para o Tratamen to de Dados Pessoais | H35: Necessário avaliar os contratos celebrados entre a Empresa Beta e terceiros. | I35: Não iniciado | J35: Não aderente | K35: Avaliação dos Contratos de terceiros e indicação da necessidade de inclusão de cláusula de proteção de dados quando aplicável
B36: 10 | C36: Tratamento dos dados pessoais - Legitimação de uso de dados | D36: S/N | E36: O uso do legítimo interesse para legitimação de dados limita-se as hipóteses apresentadas abaixo: | F36: Art. 10. O legítimo interesse do controlador somente poderá fundamentar tratamento de dados pessoais para finalidades legítimas, consideradas a partir de situações concretas, que incluem, mas não se limitam a: I – apoio e promoção de atividades do controlador; II – proteção, em relação ao titular, do exercício regular de seus direitos ou prestação de serviços que o beneficiem, respeitadas as legítimas expectativas dele e os direitos e liberdades fundamentais, nos termos desta Lei. § 1º Quando o tratamento for baseado no legítimo interesse do controlador, somente os dados pessoais estritamente necessários para a finalidade pretendida poderão ser tratados. § 2º O controlador deverá adotar medidas para garantir a transparência do tratamento de dados baseado em seu legítimo interesse. § 3º A autoridade nacional poderá solicitar ao controlador relatório de impacto à proteção de dados pessoais, quando o tratamento tiver como fundamento seu interesse legítimo, observados os segredos comercial e industrial. | G36: CAPÍTULO II - DO TRATAMENTO DE DADO S PESSOAIS Seção I Dos Requisitos para o Tratamen to de Dados Pessoais
D37: Checkbox | E37: I – apoio e promoção de atividades do controlador; | H37: Sim | I37: Em andamento | J37: Parcialmente aderente | K37: Necessário elaborar Teste de Balanceamento para verificar se o interesse legitimo da Empresa Beta é adequado.
E38: II – proteção, em relação ao titular, do exercício regular de seus direitos ou prestação de serviços que o beneficiem, respeitadas as legítimas expectativas dele e os direitos e liberdades fundamentais, nos termos desta Lei. | H38: Sim | I38: Em andamento | J38: Parcialmente aderente | K38: Necessário elaborar Teste de Balanceamento para verificar se o interesse legitimo da Empresa Beta é adequado.
B39: 11 | C39: Tratamento dos dados pessoais - Legitimação de uso de dados | D39: S/N | E39: O uso de legítimo interesse para legitimação de dados está documentado pelo controlador e operador? | F39: Art. 37. O controlador e o operador devem manter registro das operações de tratamento de dados pessoais que realizarem, especialmente quando baseado no legítimo interesse. | G39: CAPÍTULO VI - DOS AGENTES DE TRATAMENTO D E DADOS PESSOAIS Seção I Do Controlador e do Operador | H39: Não | I39: Não iniciado | J39: Não aderente | K39: Necessário elaborar Teste de Balanceamento para verificar se o interesse legitimo da Empresa Beta é adequado.
B40: 12 | C40: Tratamento dos dados pessoais - Dados públicos | D40: S/N | E40: A organização realiza tratamento de dados pessoais cujo acesso é público? | F40: Art. 7 § 3º O tratamento de dados pessoais cujo acesso é público deve considerar a finalidade, a boa-fé e o interesse público que justificaram sua disponibilização. | G40: CAPÍTULO II - DO TRATAMENTO DE DADO S PESSOAIS Seção I Dos Requisitos para o Tratamen to de Dados Pessoais | H40: Sim | I40: Não iniciado | J40: Parcialmente aderente | K40: Necessário validar se o uso de dados públicos é legitmo.
D41: Se a pergunta anterior for Sim S/N | E41: O tratamento dos dados pessoais de acesso público consideraram a finalidade, a boa-fé e o interesse público que justificaram a sua disponibilização? | F41: Art. 7 § 3º O tratamento de dados pessoais cujo acesso é público deve considerar a finalidade, a boa-fé e o interesse público que justificaram sua disponibilização. | G41: CAPÍTULO II - DO TRATAMENTO DE DADO S PESSOAIS Seção I Dos Requisitos para o Tratamen to de Dados Pessoais | H41: Necessário validar. | I41: Não iniciado | J41: Parcialmente aderente | K41: Necessário validar se o uso de dados públicos é legitmo.
B42: 13 | C42: Tratamento de dados pessoais - Obtenção / Revogação do Consentimento | D42: S/N | E42: A organização realiza tratamento de dados pessoais mediante o fornecimento de consentimento pelo titular? | F42: Art. 7º O tratamento de dados pessoais somente poderá ser realizado nas seguintes hipóteses: I - mediante o fornecimento de consentimento pelo titular; II - para o cumprimento de obrigação legal ou regulatória pelo controlador; III - pela administração pública, para o tratamento e uso compartilhado de dados necessários à execução de políticas públicas previstas em leis e regulamentos ou respaldadas em contratos, convênios ou instrumentos congêneres, observadas as disposições do Capítulo IV desta Lei; IV - para a realização de estudos por órgão de pesquisa, garantida, sempre que possível, a anonimização dos dados pessoais; V - quando necessário para a execução de contrato ou de procedimentos preliminares relacionados a contrato do qual seja parte o titular, a pedido do titular dos dados; VI - para o exercício regular de direitos em processo judicial, administrativo ou arbitral, esse último nos termos da Lei nº 9.307, de 23 de setembro de 1996 (Lei de Arbitragem); VII - para a proteção da vida ou da incolumidade física do titular ou de terceiro; VIII - para a tutela da saúde, em procedimento realizado por profissionais da área da saúde ou por entidades sanitárias; IX - quando necessário para atender aos interesses legítimos do controlador ou de terceiro, exceto no caso de prevalecerem direitos e liberdades fundamentais do titular que exijam a proteção dos dados pessoais; ou X - para a proteção do crédito, inclusive quanto ao disposto na legislação pertinente. § 1º Nos casos de aplicação do disposto nos incisos II e III do caput deste artigo e excetuadas as hipóteses previstas no art. 4º desta Lei, o titular será informado das hipóteses em que será admitido o tratamento de seus dados. § 2º A forma de disponibilização das informações previstas no § 1º e no inciso I do caput do art. 23 desta Lei poderá ser especificada pela autoridade nacional. | G42: CAPÍTULO II - DO TRATAMENTO DE DADO S PESSOAIS Seção I Dos Requisitos para o Tratamen to de Dados Pessoais | H42: Não | I42: Finalizado | J42: N/A | K42: N/A
D43: Se a pergunta anterior for Sim S/N | E43: O consentimento é obtido de forma livre (demonstra a manifestação de vontade do titular) ? | F43: Art. 8º O consentimento previsto no inciso I do art. 7º desta Lei deverá ser fornecido por escrito ou por outro meio que demonstre a manifestação de vontade do titular. cláusulas contratuais. § 2º Cabe ao controlador o ônus da prova de que o consentimento foi obtido em conformidade com o disposto nesta Lei. § 3º É vedado o tratamento de dados pessoais mediante vício de consentimento. § 4º O consentimento deverá referir-se a finalidades determinadas, e as autorizações genéricas para o tratamento de dados pessoais serão nulas. | G43: CAPÍTULO II - DO TRATAMENTO DE DADO S PESSOAIS Seção I Dos Requisitos para o Tratamen to de Dados Pessoais | H43: Não aplicável a realidade da Empresa Beta | I43: Finalizado | J43: N/A | K43: N/A
D44: Se a pergunta principal for Sim S/N | E44: Existe a possibilidade do titular dos dados revogar o consentimento a qualquer momento ? | F44: Art. 8. § 5º O consentimento pode ser revogado a qualquer momento mediante manifestação expressa do titular, por procedimento gratuito e facilitado, ratificados os tratamentos realizados sob amparo do consentimento anteriormente manifestado enquanto não houver requerimento de eliminação, nos termos do inciso VI do caput do art. 18 desta Lei. | G44: CAPÍTULO II - DO TRATAMENTO DE DADO S PESSOAIS Seção I Dos Requisitos para o Tratamen to de Dados Pessoais | H44: Não | I44: Finalizado | J44: N/A | K44: N/A
B45: 14 | C45: Tratamento dos dados pessoais - Atualização do Consentimento | D45: S/N | E45: Existe um processo para comunicar o titular sobre alterações de finalidade ou tratamento de seus dados pessoais ? | F45: Art. 8. § 6º Em caso de alteração de informação referida nos incisos I, II, III ou V do art. 9º desta Lei, o controlador deverá informar ao titular, com destaque de forma específica do teor das alterações, podendo o titular, nos casos em que o seu consentimento é exigido, revogá-lo caso discorde da alteração. Art. 9 § 2º Na hipótese em que o consentimento é requerido, se houver mudanças da finalidade para o tratamento de dados pessoais não compatíveis com o consentimento original, o controlador deverá informar previamente o titular sobre as mudanças de finalidade, podendo o titular revogar o consentimento, caso discorde das alterações. | G45: CAPÍTULO II - DO TRATAMENTO DE DADO S PESSOAIS Seção I Dos Requisitos para o Tratamen to de Dados Pessoais | H45: Não existe Política de Privacidade, e Gestão de Titular. | I45: Não iniciado | J45: Não aderente | K45: Necessário elaborar procedimento para atendimento ao Titular.
B46: 15 | C46: Tratamento dos dados pessoais - Compartilhamento de dados | D46: S/N | E46: A organização compartilha dados pessoais com outros controladores? | F46: Art. 7. § 5º O controlador que obteve o consentimento referido no inciso I do caput deste artigo que necessitar comunicar ou compartilhar dados pessoais com outros controladores deverá obter consentimento específico do titular para esse fim, ressalvadas as hipóteses de dispensa do consentimento previstas nesta Lei. | G46: CAPÍTULO II - DO TRATAMENTO DE DADO S PESSOAIS Seção I Dos Requisitos para o Tratamen to de Dados Pessoais | H46: Sim | I46: Em andamento | J46: Não aderente | K46: Necessário implementar procedimento para garantir o compartilhamento seguro de dados pessoais.
D47: Se a pergunta anterior for Sim S/N | E47: O titular dos dados pessoais obtidos mediante consentimento é informado sobre o compartilhamento dos seus dados com outros controladores? | F47: Art. 7. § 5º O controlador que obteve o consentimento referido no inciso I do caput deste artigo que necessitar comunicar ou compartilhar dados pessoais com outros controladores deverá obter consentimento específico do titular para esse fim, ressalvadas as hipóteses de dispensa do consentimento previstas nesta Lei. | G47: CAPÍTULO II - DO TRATAMENTO DE DADO S PESSOAIS Seção I Dos Requisitos para o Tratamen to de Dados Pessoais | H47: Não aplicável. | I47: Finalizado | J47: N/A | K47: N/A
B48: 16 | C48: Tratamento dos dados pessoais - Tratamento de dados obrigatória | D48: S/N | E48: A organização realiza tratamento de dados pessoais por condição obrigatória para fornecimento do produto ou serviço? | F48: Art. 9 § 3º Quando o tratamento de dados pessoais for condição para o fornecimento de produto ou de serviço ou para o exercício de direito, o titular será informado com destaque sobre esse fato e sobre os meios pelos quais poderá exercer os direitos do titular elencados no art. 18 desta Lei. | G48: CAPÍTULO II - DO TRATAMENTO DE DADO S PESSOAIS Seção I Dos Requisitos para o Tratamen to de Dados Pessoais | H48: Sim | I48: Em andamento | J48: Parcialmente aderente | K48: Necessário dar transparência por meio de Política, bem como adequar os contratos celebrados com os clientes.
D49: Se a pergunta anterior for Sim S/N | E49: O titular dos dados pessoais é informado de forma destacada sobre o tratamento de seus dados quando o mesmo é realizado como condição obrigatória para o fornecimento do produto ou serviço? | F49: Art. 9 § 3º Quando o tratamento de dados pessoais for condição para o fornecimento de produto ou de serviço ou para o exercício de direito, o titular será informado com destaque sobre esse fato e sobre os meios pelos quais poderá exercer os direitos do titular elencados no art. 18 desta Lei. | G49: CAPÍTULO II - DO TRATAMENTO DE DADO S PESSOAIS Seção I Dos Requisitos para o Tratamen to de Dados Pessoais | H49: Não | I49: Em andamento | J49: Parcialmente aderente | K49: Necessário avaliar os contratos celebrados com os clientes.
B50: 17 | C50: Tratamento dos dados pessoais sensíveis - Com ou sem consentimento | D50: Se a resposta à pergunta da linha 8 for Sim S/N | E50: O tratamento de dados pessoais sensíveis é realizado mediante consentimento do titular? | F50: Art. 11. O tratamento de dados pessoais sensíveis somente poderá ocorrer nas seguintes hipóteses: I - quando o titular ou seu responsável legal consentir, de forma específica e destacada, para finalidades específicas; | G50: CAPÍTULO II - DO TRATAMENTO DE DADO S PESSOAIS Seção II Do Tratamento de Dados P essoais Sensíveis | H50: Não | I50: Finalizado | J50: N/A | K50: N/A
D51: Se a pergunta anterior for Sim S/N | E51: O consentimento do titular para o tratamento de dados sensíveis é dado de forma específica e destacada para finalidades específicas? | F51: Art. 11. O tratamento de dados pessoais sensíveis somente poderá ocorrer nas seguintes hipóteses: I - quando o titular ou seu responsável legal consentir, de forma específica e destacada, para finalidades específicas; | G51: CAPÍTULO II - DO TRATAMENTO DE DADO S PESSOAIS Seção II Do Tratamento de Dados P essoais Sensíveis | H51: Não | I51: Finalizado | J51: N/A | K51: N/A
D52: Se a pergunta principal for Não S/N | E52: O tratamento de dados pessoais sensíveis, sem consentimento, é realizado para alguma das hipóteses abaixo? | F52: Art. 11. O tratamento de dados pessoais sensíveis somente poderá ocorrer nas seguintes hipóteses: II - sem fornecimento de consentimento do titular, nas hipóteses em que for indispensável para: a) cumprimento de obrigação legal ou regulatória pelo controlador; b) tratamento compartilhado de dados necessários à execução, pela administração pública, de políticas públicas previstas em leis ou regulamentos; c) realização de estudos por órgão de pesquisa, garantida, sempre que possível, a anonimização dos dados pessoais sensíveis; d) exercício regular de direitos, inclusive em contrato e em processo judicial, administrativo e arbitral, este último nos termos da Lei nº 9.307, de 23 de setembro de 1996 (Lei de Arbitragem); e) proteção da vida ou da incolumidade física do titular ou de terceiro; f) tutela da saúde, em procedimento realizado por profissionais da área da saúde ou por entidades sanitárias; ou g) garantia da prevenção à fraude e à segurança do titular, nos processos de identificação e autenticação de cadastro em sistemas eletrônicos, resguardados os direitos mencionados no art. 9º desta Lei e exceto no caso de prevalecerem direitos e liberdades fundamentais do titular que exijam a proteção dos dados pessoais. | G52: CAPÍTULO II - DO TRATAMENTO DE DADO S PESSOAIS Seção II Do Tratamento de Dados P essoais Sensíveis
D53: Checkbox | E53: a) cumprimento de obrigação legal ou regulatória pelo controlador; | H53: Não | I53: Finalizado | J53: N/A | K53: N/A
E54: b) tratamento compartilhado de dados necessários à execução, pela administração pública, de políticas públicas previstas em leis ou regulamentos; | H54: N/A | I54: Finalizado | J54: N/A | K54: N/A
E55: c) realização de estudos por órgão de pesquisa, garantida, sempre que possível, a anonimização dos dados pessoais sensíveis; | H55: N/A | I55: Finalizado | J55: N/A | K55: N/A
E56: d) exercício regular de direitos, inclusive em contrato e em processo judicial, administrativo e arbitral, este último nos termos da Lei nº 9.307, de 23 de setembro de 1996 (Lei de Arbitragem); | H56: Sim | I56: Em andamento | J56: Parcialmente aderente | K56: Necessário dar transparência por meio de Política.
E57: e) proteção da vida ou da incolumidade física do titular ou de terceiro; | H57: N/A | I57: Finalizado | J57: N/A | K57: N/A
E58: f) tutela da saúde, em procedimento realizado por profissionais da área da saúde ou por entidades sanitárias; ou | H58: N/A | I58: Finalizado | J58: N/A | K58: N/A
E59: g) garantia da prevenção à fraude e à segurança do titular, nos processos de identificação e autenticação de cadastro em sistemas eletrônicos, resguardados os direitos mencionados no art. 15 desta Lei e excetuado o caso em que prevaleçam direitos e liberdades fundamentais do titular que exijam a proteção dos dados pessoais | H59: N/A | I59: Finalizado | J59: N/A | K59: N/A
B60: 18 | C60: Tratamento dos dados pessoais sensíveis - Compartilhamento entre controladores | D60: Se a resposta à pergunta da linha 8 for Sim S/N | E60: Os dados pessoais sensíveis são compartilhados com outros controladores ? | F60: Art. 11. § 3º A comunicação ou o uso compartilhado de dados pessoais sensíveis entre controladores com objetivo de obter vantagem econômica poderá ser objeto de vedação ou de regulamentação por parte da autoridade nacional, ouvidos os órgãos setoriais do Poder Público, no âmbito de suas competências. § 4º É vedada a comunicação ou o uso compartilhado entre controladores de dados pessoais sensíveis referentes à saúde com objetivo de obter vantagem econômica, exceto nos casos de portabilidade de dados quando consentido pelo titular. | G60: CAPÍTULO II - DO TRATAMENTO DE DADO S PESSOAIS Seção II Do Tratamento de Dados P essoais Sensíveis | H60: Não | I60: Não iniciado | J60: Não aderente | K60: N/A
B61: 19 | C61: Tratamento dos dados pessoais sensíveis - Compartilhamento entre controladores | D61: Se a pergunta anterior for Sim S/N | E61: A finalidade do compartilhamento de dados pessoais sensíveis está associado a obter vantagem econômica ? | F61: Art. 11. § 3º A comunicação ou o uso compartilhado de dados pessoais sensíveis entre controladores com objetivo de obter vantagem econômica poderá ser objeto de vedação ou de regulamentação por parte da autoridade nacional, ouvidos os órgãos setoriais do Poder Público, no âmbito de suas competências. § 4º É vedada a comunicação ou o uso compartilhado entre controladores de dados pessoais sensíveis referentes à saúde com objetivo de obter vantagem econômica, exceto nos casos de portabilidade de dados quando consentido pelo titular. | G61: CAPÍTULO II - DO TRATAMENTO DE DADO S PESSOAIS Seção II Do Tratamento de Dados P essoais Sensíveis | H61: Não. | I61: Não iniciado | J61: Não aderente | K61: N/A
B62: 20 | C62: Tratamento dos dados pessoais - Anonimização | D62: S/N | E62: Existem dados pessoais anonimizados? | F62: Art. 12. Os dados anonimizados não serão considerados dados pessoais para os fins desta Lei, salvo quando o processo de anonimização ao qual foram submetidos for revertido, utilizando exclusivamente meios próprios, ou quando, com esforços razoáveis, puder ser revertido. § 1º A determinação do que seja razoável deve levar em consideração fatores objetivos, tais como custo e tempo necessários para reverter o processo de anonimização, de acordo com as tecnologias disponíveis, e a utilização exclusiva de meios próprios. Art 18. § 7º A portabilidade dos dados pessoais a que se refere o inciso V do caput deste artigo não inclui dados que já tenham sido anonimizados pelo controlador. | G62: CAPÍTULO II - DO TRATAMENTO DE DADO S PESSOAIS Seção II Do Tratamento de Dados P essoais Sensíveis Seção III Do Tratamento de Dados Pessoais de Crianças e de Adolescentes | H62: Não | I62: Finalizado | J62: N/A | K62: N/A
D63: Se a pergunta anterior for Sim S/N | E63: O processo de anonimização pode ser revertido utilizando exclusivamente meios próprios ou com esforços razoáveis? | F63: Art. 12. Os dados anonimizados não serão considerados dados pessoais para os fins desta Lei, salvo quando o processo de anonimização ao qual foram submetidos for revertido, utilizando exclusivamente meios próprios, ou quando, com esforços razoáveis, puder ser revertido. § 1º A determinação do que seja razoável deve levar em consideração fatores objetivos, tais como custo e tempo necessários para reverter o processo de anonimização, de acordo com as tecnologias disponíveis, e a utilização exclusiva de meios próprios. Art 18. § 7º A portabilidade dos dados pessoais a que se refere o inciso V do caput deste artigo não inclui dados que já tenham sido anonimizados pelo controlador. | G63: CAPÍTULO II - DO TRATAMENTO DE DADO S PESSOAIS Seção II Do Tratamento de Dados P essoais Sensíveis Seção III Do Tratamento de Dados Pessoais de Crianças e de Adolescentes | H63: Não | I63: Finalizado | J63: N/A | K63: N/A
B64: 21 | C64: Tratamento dos dados pessoais sensíveis - Estudos e pesquisas de saúde pública | D64: S/N | E64: A organização tem acesso a dados pessoais obtidos por meio de realização de estudos em saúde pública. | F64: Art. 13. Na realização de estudos em saúde pública, os órgãos de pesquisa poderão ter acesso a bases de dados pessoais, que serão tratados exclusivamente dentro do órgão e estritamente para a finalidade de realização de estudos e pesquisas e mantidos em ambiente controlado e seguro, conforme práticas de segurança previstas em regulam ento específico e que incluam, sempre que possível, a anonimização ou pseudonimização dos dados, bem como considerem os devidos padrões éticos relacionados a estudos e pesquisas. § 1º A divulgação dos resultados ou de qualquer excerto do estudo ou da pesquisa de que trata o caput deste artigo em nenhuma hipótese poderá revelar dados pessoais. § 2º O órgão de pesquisa será o responsável pela segurança da informação prevista no caput deste artigo, não permitida, em circunstância alguma, a transferência dos dados a terceiro. § 3º O acesso aos dados de que trata este artigo será objeto de regulamentação por parte da autoridade nacional e das autoridades da área de saúde e sanitárias, no âmbito de suas competências. § 4º Para os efeitos deste artigo, a pseudonimização é o tratamento por meio do qual um dado perde a possibilidade de associação, direta ou indireta, a um indivíduo, senão pelo uso de informação adicional mantida separadamente pelo controlador em ambiente controlado e seguro. | G64: CAPÍTULO II - DO TRATAMENTO DE DADOS PESSOAIS - Seção II Do Tratamento de Dados P essoais Sensíveis | H64: Tal atividade não se aplica à Empresa Beta. | I64: Finalizado | J64: N/A | K64: N/A
B65: 2 | D65: Se a pergunta anterior for Sim S/N | E65: O tratamento de dados pessoais obtidos por meio de realização de estudos em saúde pública é realizado estritamente para a finalidade de realização de estudos e pesquisas e mantidos em ambiente controlado e seguro? | F65: Art. 13. Na realização de estudos em saúde pública, os órgãos de pesquisa poderão ter acesso a bases de dados pessoais, que serão tratados exclusivamente dentro do órgão e estritamente para a finalidade de realização de estudos e pesquisas e mantidos em ambiente controlado e seguro, conforme práticas de segurança previstas em regulam ento específico e que incluam, sempre que possível, a anonimização ou pseudonimização dos dados, bem como considerem os devidos padrões éticos relacionados a estudos e pesquisas. § 1º A divulgação dos resultados ou de qualquer excerto do estudo ou da pesquisa de que trata o caput deste artigo em nenhuma hipótese poderá revelar dados pessoais. § 2º O órgão de pesquisa será o responsável pela segurança da informação prevista no caput deste artigo, não permitida, em circunstância alguma, a transferência dos dados a terceiro. § 3º O acesso aos dados de que trata este artigo será objeto de regulamentação por parte da autoridade nacional e das autoridades da área de saúde e sanitárias, no âmbito de suas competências. § 4º Para os efeitos deste artigo, a pseudonimização é o tratamento por meio do qual um dado perde a possibilidade de associação, direta ou indireta, a um indivíduo, senão pelo uso de informação adicional mantida separadamente pelo controlador em ambiente controlado e seguro. | G65: CAPÍTULO II - DO TRATAMENTO DE DADOS PESSOAIS - Seção II Do Tratamento de Dados P essoais Sensíveis | H65: Tal atividade não se aplica à Empresa Beta. | I65: Finalizado | J65: N/A | K65: N/A
D66: Se a pergunta prinicpal for Sim S/N | E66: É realizado o compartilhamento de dados pessoais obtidos por meio de realização de estudos em saúde pública com terceiros? | F66: Art. 13. Na realização de estudos em saúde pública, os órgãos de pesquisa poderão ter acesso a bases de dados pessoais, que serão tratados exclusivamente dentro do órgão e estritamente para a finalidade de realização de estudos e pesquisas e mantidos em ambiente controlado e seguro, conforme práticas de segurança previstas em regulam ento específico e que incluam, sempre que possível, a anonimização ou pseudonimização dos dados, bem como considerem os devidos padrões éticos relacionados a estudos e pesquisas. § 1º A divulgação dos resultados ou de qualquer excerto do estudo ou da pesquisa de que trata o caput deste artigo em nenhuma hipótese poderá revelar dados pessoais. § 2º O órgão de pesquisa será o responsável pela segurança da informação prevista no caput deste artigo, não permitida, em circunstância alguma, a transferência dos dados a terceiro. § 3º O acesso aos dados de que trata este artigo será objeto de regulamentação por parte da autoridade nacional e das autoridades da área de saúde e sanitárias, no âmbito de suas competências. § 4º Para os efeitos deste artigo, a pseudonimização é o tratamento por meio do qual um dado perde a possibilidade de associação, direta ou indireta, a um indivíduo, senão pelo uso de informação adicional mantida separadamente pelo controlador em ambiente controlado e seguro. | G66: CAPÍTULO II - DO TRATAMENTO DE DADOS PESSOAIS - Seção II Do Tratamento de Dados P essoais Sensíveis | H66: Tal atividade não se aplica à Empresa Beta. | I66: Finalizado | J66: N/A | K66: N/A
B67: 22 | C67: Tratamento dos dados pessoais sensíveis - Crianças e adolescentes - Consentimento | D67: S/N | E67: O tratamento de dados pessoais de crianças e adolescentes é realizado mediante coleta de consentimento dos pais ou responsaveis do titular ? | F67: Art. 14. O tratamento de dados pessoais de crianças e de adolescentes deverá ser realizado em seu melhor interesse, nos termos deste artigo e da legislação pertinente. § 1º O tratamento de dados pessoais de crianças deverá ser realizado com o consentimento específico e em destaque dado por pelo menos um dos pais ou pelo responsável legal. § 3º Poderão ser coletados dados pessoais de crianças sem o consentimento a que se refere o § 1º deste artigo quando a coleta for necessária para contatar os pais ou o responsável legal, utilizados uma única vez e sem armazenamento, ou para sua proteção, e em nenhum caso poderão ser repassados a terceiro sem o consentimento de que trata o § 1º deste artigo. § 5º O controlador deve realizar todos os esforços razoáveis para verificar que o consentimento a que se refere o § 1º deste artigo foi dado pelo responsável pela criança, consideradas as tecnologias disponíveis. § 6º As informações sobre o tratamento de dados referidas neste artigo deverão ser fornecidas de maneira simples, clara e acessível, consideradas as características físico-motoras, perceptivas, sensoriais, intelectuais e mentais do usuário, com uso de recursos audiovisuais quando adequado, de forma a proporcionar a informação necessária aos pais ou ao responsável legal e adequada ao entendimento da criança. | G67: CAPÍTULO II - DO TRATAMENTO DE DADOS PESSOAIS - Seção III Do Tratamento de Dados Pessoais de Crianças e de Adolescentes | H67: Não ocorre o tratamento de dados pessoais de crianças e/ou adolescentes. | I67: Finalizado | J67: N/A | K67: N/A
B68: 23 | C68: Tratamento dos dados pessoais sensíveis - Crianças e adolescentes - Procedimentos públicos | D68: S/N | E68: No caso de tratamento de dados pessoais de crianças e adolescentes, o tipo de dado coletado, a forma de sua utilização e os procedimentos para exercício dos direitos do titular (criança e adolescente) estão disponíveis em canal público ? | F68: Art. 14 § 2º No tratamento de dados de que trata o § 1º deste artigo, os controladores deverão manter pública a informação sobre os tipos de dados coletados, a forma de sua utilização e os procedimentos para o exercício dos direitos a que se refere o art. 18 desta Lei. | G68: CAPÍTULO II - DO TRATAMENTO DE DADOS PESSOAIS - Seção III Do Tratamento de Dados Pessoais de Crianças e de Adolescentes | H68: N/A | I68: Finalizado | J68: N/A | K68: N/A
B69: 24 | C69: Tratamento dos dados pessoais sensíveis - Crianças e adolescentes - Jogos, aplicações de internet e outras atividades | D69: S/N | E69: Dados pessoais de crianças e adolescentes são solicitadas como condição para acesso a jogos, aplicações de internet ou outras atividades além do necessário para prestação do serviço ? | F69: Art. 14 § 4º Os controladores não deverão condicionar a participação dos titulares de que trata o § 1º deste artigo em jogos, aplicações de internet ou outras tividades ao fornecimento de informações pessoais além das estritamente necessárias à atividade. | G69: CAPÍTULO II - DO TRATAMENTO DE DADOS PESSOAIS - Seção III Do Tratamento de Dados Pessoais de Crianças e de Adolescentes | H69: N/A | I69: Finalizado | J69: N/A | K69: N/A
B70: 25 | C70: Término do Tratamento de Dados | D70: S/N | E70: Existem prazos de retenção estabelecidos no inventário dos dados pessoais tratados e/ou políticas e procedimentos da organização? | F70: Art. 21. O término do tratamento de dados pessoais ocorrerá nas seguintes hipóteses: I – verificação de que a finalidade foi alcançada ou de que os dados deixaram de ser necessários ou pertinentes ao alcance da finalidade específica almejada; II – fim do período de tratamento; III - comunicação do titular, inclusive no exercício de seu direito de revogação do consentimento conforme disposto no § 5º do art. 8º desta Lei, resguardado o interesse público; ou IV - determinação da autoridade nacional, quando houver violação ao disposto nesta Lei. | H70: Não. | I70: Não iniciado | J70: Não aderente | K70: Necessário elaborar Política de Retenção de Dados
B71: 26 | C71: Término do Tratamento de Dados | D71: S/N | E71: Existe previsão de término do tratamento de dados pessoais em alguma das hipóteses abaixo? | F71: Art. 21. O término do tratamento de dados pessoais ocorrerá nas seguintes hipóteses: I – verificação de que a finalidade foi alcançada ou de que os dados deixaram de ser necessários ou pertinentes ao alcance da finalidade específica almejada; II – fim do período de tratamento; III - comunicação do titular, inclusive no exercício de seu direito de revogação do consentimento conforme disposto no § 5º do art. 8º desta Lei, resguardado o interesse público; ou IV - determinação da autoridade nacional, quando houver violação ao disposto nesta Lei. | G71: CAPÍTULO III DOS DIREITOS DO TI TULAR
D72: Checkbox | E72: I – verificação de que a finalidade foi alcançada ou de que os dados deixaram de ser necessários ou pertinentes ao alcance da finalidade específica almejada; | H72: Não. | I72: Não iniciado | J72: Não aderente | K72: Necessário elaborar Política de Retenção de Dados
E73: II – fim do período de tratamento; | H73: Não. | I73: Não iniciado | J73: Não aderente | K73: Necessário elaborar Política de Retenção de Dados
E74: III – comunicação do titular, inclusive no exercício de seu direito de revogação do consentimento conforme disposto no § 5º do art. 14 desta Lei, resguardado o interesse público; ou | H74: Não. | I74: Não iniciado | J74: Não aderente | K74: Necessário elaborar Política de Retenção de Dados
E75: IV - determinação da autoridade nacional, quando houver violação ao disposto nesta Lei. | H75: Não. | I75: Não iniciado | J75: Não aderente | K75: Necessário elaborar Política de Retenção de Dados
B76: 27 | C76: Término do Tratamento de Dados | D76: S/N | E76: Após o término do tratamento os dados pessoais são eliminados? | F76: Art. 16. Os dados pessoais serão eliminados após o término de seu tratamento, no âmbito e nos limites técnicos das atividades, autorizada a conservação para as seguintes finalidades: I - cumprimento de obrigação legal ou regulatória pelo controlador; II - estudo por órgão de pesquisa, garantida, sempre que possível, a anonimização dos dados pessoais; III - transferência a terceiro, desde que respeitados os requisitos de tratamento de dados dispostos nesta Lei; ou IV - uso exclusivo do controlador, vedado seu acesso por terceiro, e desde que anonimizados os dados. | G76: CAPÍTULO II - DO TRATAMENTO DE DADOS PESSOAIS - Seção IV Do Término do Tratame nto de Dados | H76: Não. | I76: Não iniciado | J76: Não aderente | K76: Necessário elaborar Política de Retenção de Dados
B77: 28 | C77: Término do Tratamento de Dados | D77: S/N | E77: Quando não eliminados, os dados pessoais são conservados para alguma das finalidades abaixo? | F77: Art. 16. Os dados pessoais serão eliminados após o término de seu tratamento, no âmbito e nos limites técnicos das atividades, autorizada a conservação para as seguintes finalidades: I - cumprimento de obrigação legal ou regulatória pelo controlador; II - estudo por órgão de pesquisa, garantida, sempre que possível, a anonimização dos dados pessoais; III - transferência a terceiro, desde que respeitados os requisitos de tratamento de dados dispostos nesta Lei; ou IV - uso exclusivo do controlador, vedado seu acesso por terceiro, e desde que anonimizados os dados. | G77: CAPÍTULO II - DO TRATAMENTO DE DADOS PESSOAIS - Seção IV Do Término do Tratame nto de Dados
D78: Checkbox | E78: I – cumprimento de obrigação legal ou regulatória pelo controlador; | H78: Não. | I78: Não iniciado | J78: Não aderente | K78: Necessário elaborar Política de Retenção de Dados
E79: II – estudo por órgão de pesquisa, garantida, sempre que possível, a anonimização dos dados pessoais; | H79: Não. | I79: Não iniciado | J79: Não aderente | K79: Necessário elaborar Política de Retenção de Dados
E80: III – transferência a terceiro, desde que respeitados os requisitos de tratamento de dados dispostos nesta Lei; ou | H80: Não. | I80: Não iniciado | J80: Não aderente | K80: Necessário elaborar Política de Retenção de Dados
E81: IV – uso exclusivo do controlador, vedado seu acesso por terceiro, e desde que anonimizados os dados. | H81: Não. | I81: Não iniciado | J81: Não aderente | K81: Necessário elaborar Política de Retenção de Dados
B82: 29 | C82: Transferência internacional de dados | D82: S/N | E82: A organização realiza a transferência de dados pessoais para outros países? | F82: Art. 33. A transferência internacional de dados pessoais somente é permitida nos seguintes casos: I - para países ou organismos internacionais que proporcionem grau de proteção de dados pessoais adequado ao previsto nesta Lei; II - quando o controlador oferecer e comprovar garantias de cumprimento dos princípios, dos direitos do titular e do regime de proteção de dados previstos nesta Lei, na forma de: a) cláusulas contratuais específicas para determinada transferência; b) cláusulas-padrão contratuais; c) normas corporativas globais; d) selos, certificados e códigos de conduta regularmente emitidos; III - quando a transferência for necessária para a cooperação jurídica internacional entre órgãos públicos de inteligência, de investigação e de persecução, de acordo com os instrumentos de direito internacional; IV - quando a transferência for necessária para a proteção da vida ou da incolumidade física do titular ou de terceiro; V - quando a autoridade nacional autorizar a transferência; VI - quando a transferência resultar em compromisso assumido em acordo de cooperação internacional; VII - quando a transferência for necessária para a execução de política pública ou atribuição legal do serviço público, sendo dada publicidade nos termos do inciso I do caput do art. 23 desta Lei; VIII - quando o titular tiver fornecido o seu consentimento específico e em destaque para a transferência, com informação prévia sobre o caráter internacional da operação, distinguindo claramente esta de outras finalidades; ou IX - quando necessário para atender as hipóteses previstas nos incisos II, V e VI do art. 7º desta Lei. | G82: CAPÍTULO V - DA TRANSFERÊNCIA INTERNAC IONAL DE DADOS | H82: Sim | I82: Em andamento | J82: Não aderente | K82: Necessário analisar Contrato celebrado com terceiro, bem como elaborar Política de Transferência Internacional de Dados.
D83: Se a pergunta anterior for Sim | E83: Para quais países é realizada a transferência de dados pessoais? | H83: Estados Unidos, Reino Unido, Singapura, Alemanha, e Africa do Sul. | I83: Em andamento | J83: Não aderente | K83: Necessário analisar Contrato celebrado com terceiro, bem como elaborar Política de Transferência Internacional de Dados.
D84: Se a pergunta prinicpal for Sim S/N | E84: A transferência de dados pessoais para outros países baseia-se em um dos cenários abaixo:
D85: Checkbox | E85: I – para países ou organismos internacionais que proporcionem grau de proteção de dados pessoais adequado ao previsto nesta Lei; | H85: A ANPD ainda não definiu regras do nível de proteção em âmbito global. | I85: Finalizado | J85: N/A | K85: Pendente de definição pela ANPD.
E86: II – o controlador oferece e comprova garantias de cumprimento dos princípios, dos direitos do titular e do regime de proteção de dados previstos nesta Lei, na forma de: a) cláusulas contratuais específicas para determinada transferência; b) cláusulas-padrão contratuais; c) normas corporativas globais; d) selos, certificados e códigos de conduta regularmente emitidos; | H86: Sim | I86: Não iniciado | J86: Não aderente | K86: Necessário analisar Contrato celebrado com terceiro.
E87: III – necessária à cooperação jurídica internacional entre órgãos públicos de inteligência, de investigação e de persecução, de acordo com os instrumentos de direito internacional; | H87: Não | I87: Finalizado | J87: N/A | K87: N/A
E88: IV – necessária à proteção da vida ou da incolumidade física do titular ou de terceiro; | H88: Não | I88: Finalizado | J88: N/A | K88: N/A
E89: V – autorizada pela autoridade nacional; | H89: Não | I89: Finalizado | J89: N/A | K89: N/A
E90: VI - quando a transferência resultar em compromisso assumido em acordo de cooperação internacional; | H90: Não | I90: Finalizado | J90: N/A | K90: N/A
E91: VII – necessária à execução de política pública ou ao cumprimento de atribuição legal do serviço público, sendo dada publicidade nos termos do inciso I do caput do art. 23 desta Lei; | H91: Não | I91: Finalizado | J91: N/A | K91: N/A
E92: VIII – o titular forneceu consentimento específico e em destaque, com informação prévia sobre o caráter internacional da operação, distinguindo claramente esta de outras finalidades; | H92: Não | I92: Finalizado | J92: N/A | K92: N/A
B93: 30 | C93: Agentes de tratamento de dados | D93: S/N | E93: Existe um processo estabelecido pelo controlador para verificar o tratamento realizado pelo operador ? O tratamento realizado respeita e limita-se as instruções repassadas pelo controlador ? | F93: Art. 39. O operador deverá realizar o tratamento segundo as instruções fornecidas pelo controlador, que verificará a observância das próprias instruções e das normas sobre a matéria. | G93: CAPÍTULO VI - DOS AGENTES DE TRATAMENTO D E DADOS PESSOAIS Seção I Do Controlador e do Operador | H93: Não existe. | I93: Não iniciado | J93: Não aderente | K93: Implementar processo de gestão de terceiros
C94: Agentes de tratamento de dados | D94: S/N | E94: O tratamento realizado respeita e limita-se as instruções repassadas pelo controlador? | F94: Art. 39. O operador deverá realizar o tratamento segundo as instruções fornecidas pelo controlador, que verificará a observância das próprias instruções e das normas sobre a matéria. | G94: CAPÍTULO VI - DOS AGENTES DE TRATAMENTO D E DADOS PESSOAIS Seção I Do Controlador e do Operador | H94: Inexiste procedimento para gestão de terceiros. | I94: Não iniciado | J94: Não aderente | K94: Implementar processo de gestão de terceiros
B95: 31 | C95: DPO | D95: S/N | E95: O DPO (encarregado pelo tratamento de dados pessoais) foi nomeado? | F95: Art. 41. O controlador deverá indicar encarregado pelo tratamento de dados pessoais. § 1º A identidade e as informações de contato do encarregado deverão ser divulgadas publicamente, de forma clara e objetiva, preferencialmente no sítio eletrônico do controlador. | G95: CAPÍTULO VI - DOS AGENTES DE TRATAMENTO D E DADOS PESSOAIS Seção II Do Encarregado pelo Tratamen to de Dados Pessoais | H95: Sim | I95: Em andamento | J95: Parcialmente aderente | K95: Validar se o DPO no ambito internacional será o mesmo do Brasil.
D96: S/N | E96: As informações de contato do DPO foram divulgadas publicamente (ex. site)? | F96: Art. 41. O controlador deverá indicar encarregado pelo tratamento de dados pessoais. § 1º A identidade e as informações de contato do encarregado deverão ser divulgadas publicamente, de forma clara e objetiva, preferencialmente no sítio eletrônico do controlador. | G96: CAPÍTULO VI - DOS AGENTES DE TRATAMENTO D E DADOS PESSOAIS Seção II Do Encarregado pelo Tratamen to de Dados Pessoais | H96: Sim | I96: Em andamento | J96: Parcialmente aderente | K96: Publicar informação
D97: S/N | E97: Os papéis e responsabilidade do DPO está definidos e documentados e contemplam, no mínimo, as responsabilidades descritas abaixo: I – receber reclamações e comunicações dos titulares, prestar esclarecimentos e adotar providências; II – receber comunicações da autoridade nacional e adotar providências; III – orientar os funcionários e os contratados da entidade a respeito das práticas a serem adotadas em relação à proteção de dados pessoais; IV – executar as demais atribuições determinadas pelo controlador ou estabelecidas em normas complementares. | F97: Art. 41. O controlador deverá indicar encarregado pelo tratamento de dados pessoais. § 2º As atividades do encarregado consistem em: I - aceitar reclamações e comunicações dos titulares, prestar esclarecimentos e adotar providências; II - receber comunicações da autoridade nacional e adotar providências; III - orientar os funcionários e os contratados da entidade a respeito das práticas a serem tomadas em relação à proteção de dados pessoais; e IV - executar as demais atribuições determinadas pelo controlador ou estabelecidas em normas complementares. | G97: CAPÍTULO VI - DOS AGENTES DE TRATAMENTO D E DADOS PESSOAIS Seção II Do Encarregado pelo Tratamen to de Dados Pessoais | H97: inexiste procedimento de nomeação do Encarregado | I97: Não iniciado | J97: Não aderente | K97: Elaboração de Normas para a função do DPO.
B98: 32 | C98: Segurança da Informação | D98: S/N | E98: Os dados pessoais estão armazenados em sistemas com controles de acesso? | F98: Art. 46. Os agentes de tratamento devem adotar medidas de segurança, técnicas e administrativas aptas a proteger os dados pessoais de acessos não autorizados e de situações acidentais ou ilícitas de destruição, perda, alteração, comunicação ou qualquer forma de tratamento inadequado ou ilícito. | G98: CAPÍTULO VII - DA SEGURANÇA E DAS BOA S PRÁTICAS Seção I Da Segurança e do Sig ilo de Dados | H98: Sim | I98: Finalizado | J98: Aderente | K98: N/A
D99: S/N | E99: Os acessos são revisados periodicamente? | F99: Art. 46. Os agentes de tratamento devem adotar medidas de segurança, técnicas e administrativas aptas a proteger os dados pessoais de acessos não autorizados e de situações acidentais ou ilícitas de destruição, perda, alteração, comunicação ou qualquer forma de tratamento inadequado ou ilícito. | G99: CAPÍTULO VII - DA SEGURANÇA E DAS BOA S PRÁTICAS Seção I Da Segurança e do Sig ilo de Dados | H99: Não | I99: Não iniciado | J99: Não aderente | K99: Recomenda-se revisar e auditar periodicamente os acessos para evitar que possíveis falhas deste controle resultem em incidentes de SI e de dados.
D100: S/N | E100: Como os acessos são concedidos e revogados? | F100: Art. 46. Os agentes de tratamento devem adotar medidas de segurança, técnicas e administrativas aptas a proteger os dados pessoais de acessos não autorizados e de situações acidentais ou ilícitas de destruição, perda, alteração, comunicação ou qualquer forma de tratamento inadequado ou ilícito. | G100: CAPÍTULO VII - DA SEGURANÇA E DAS BOA S PRÁTICAS Seção I Da Segurança e do Sig ilo de Dados | H100: A concessão/revogação de acessos não é centralizada, sendo que parte dos acesos são administrados pela equipe de TI, parte está sob a responsabilidade do RH. | I100: Em andamento | J100: Parcialmente aderente | K100: Estabelecer e aplicar uma política de liberação e revogação de acessos, se possível centralizada.
D101: S/N | E101: Os dados pessoais são submetidos a processo de backup periódico? | F101: Art. 46. Os agentes de tratamento devem adotar medidas de segurança, técnicas e administrativas aptas a proteger os dados pessoais de acessos não autorizados e de situações acidentais ou ilícitas de destruição, perda, alteração, comunicação ou qualquer forma de tratamento inadequado ou ilícito. | G101: CAPÍTULO VII - DA SEGURANÇA E DAS BOA S PRÁTICAS Seção I Da Segurança e do Sig ilo de Dados | H101: Sim, mas está em processo de revisão | I101: Em andamento | J101: Parcialmente aderente | K101: Rever a estratégia de backup com criptografia e isolamento do armazenamento (offline) para evitar que um ransomware por exemplo afete inclusive os backups e ocorra a perda de dados. Prever que ao menos uma cópia seja armazenada externamente. Assegurar que os fornecedores de soluções/sistemas que também realizam os respectivos backups, estejam em conformidade com a Política de Backup da Empresa.
D102: S/N | E102: Os dados pessoais são parte do Plano de Continuidade de Negócios e Disaster Recovery Plan da organização? | F102: Art. 46. Os agentes de tratamento devem adotar medidas de segurança, técnicas e administrativas aptas a proteger os dados pessoais de acessos não autorizados e de situações acidentais ou ilícitas de destruição, perda, alteração, comunicação ou qualquer forma de tratamento inadequado ou ilícito. | G102: CAPÍTULO VII - DA SEGURANÇA E DAS BOA S PRÁTICAS Seção I Da Segurança e do Sig ilo de Dados | H102: Não, não há Plano de Continuidade de Negócios formalmente aplicado. | I102: Não iniciado | J102: Não aderente | K102: Desenvolver um plano de continuidade de negócios e disaster recovery adequado a Empresa.
D103: S/N | E103: Os dados pessoais são protegidos por técnicas e processos que previnem sua alteração e perda de integridade ? | F103: Art. 46. Os agentes de tratamento devem adotar medidas de segurança, técnicas e administrativas aptas a proteger os dados pessoais de acessos não autorizados e de situações acidentais ou ilícitas de destruição, perda, alteração, comunicação ou qualquer forma de tratamento inadequado ou ilícito. | G103: CAPÍTULO VII - DA SEGURANÇA E DAS BOA S PRÁTICAS Seção I Da Segurança e do Sig ilo de Dados | H103: Não, não há criptografia, cultura/processo de gestão de incidentes, análise de vulnerabilidades ou monitoramento, nem práticas de testes de intrusão periódicos. | I103: Não iniciado | J103: Não aderente | K103: Incluir procedimento de criptografia em dados sensiveis. Incluir práticas de gestão de incidentes e monitoramento de acessos anômalos.
D104: Se a pergunta prinicpal for Sim | E104: Quais técnicas e processos que previnem a alteração e perda de integridade de dados pessoais são utilizadas? | F104: Art. 46. Os agentes de tratamento devem adotar medidas de segurança, técnicas e administrativas aptas a proteger os dados pessoais de acessos não autorizados e de situações acidentais ou ilícitas de destruição, perda, alteração, comunicação ou qualquer forma de tratamento inadequado ou ilícito. | G104: CAPÍTULO VII - DA SEGURANÇA E DAS BOA S PRÁTICAS Seção I Da Segurança e do Sig ilo de Dados | H104: Não Possui | I104: Não iniciado | J104: Não aderente | K104: Definir uma Política de Classificação, rotulagem e manuseio seguro da informação
...

Sheet Analítico
B2: Analítico
B5: Agentes de tratamento de dados | D5: 0 | E5: DPIA | G5: =COUNTIF(F7:F9,"Aderente")/COUNTA(F7:F9) -> 0 | H5: DPO | J5: =COUNTIF(I7:I8,"Aderente")/COUNTA(I7:I8) -> 0
B6: Exigência | C6: Adesão | D6: 1 | E6: Exigência | F6: Adesão | G6: =COUNTIF(F7:F9,"Não Aderente")/COUNTA(F7:F9) -> 1 | H6: Exigência | I6: Adesão | J6: =COUNTIF(I7:I8,"Não Aderente")/COUNTA(I7:I8) -> 1
B7: Existência de processo | C7: =Controles!J93 -> Não aderente | D7: 0 | E7: Considera 10 princípios da boa-fé | F7: =Controles!J25 -> Não aderente | G7: =COUNTIF(F7:F9,"Parcialmente Aderente")/COUNTA(F7:F9) -> 0 | H7: Nomeação do DPO e divulgação | I7: Não aderente | J7: =COUNTIF(I7:I8,"Parcialmente Aderentemente Aderente")/COUNTA(I7:I8) -> 0
D8: 0 | E8: Processo documentado | F8: =Controles!J26 -> Não aderente | G8: =COUNTIF(F7:F9,"N/A")/COUNTA(F7:F9) -> 0 | H8: Definição de responsabilidades | I8: Não aderente | J8: =COUNTIF(I7:I8,"N/A")/COUNTA(I7:I8) -> 0
B9: Direito dos titulares dos dados | D9: 0 | E9: Geração de relatório de impacto | F9: =Controles!J27 -> Não aderente
B10: Exigência | C10: Adesão | D10: 0.5 | H10: Programa de governança em privacidade | J10: =COUNTIF(I12:I13,"Aderente")/COUNTA(I12:I13) -> 0
B11: Existência de processo de emissão de requisição | C11: =Controles!J28 -> Não aderente | D11: 0.33333333 | E11: Gestão de incidentes de privacidade | G11: =COUNTIF(F13:F13,"Aderente")/COUNTA(F13:F13) -> 0 | H11: Exigência | I11: Adesão | J11: =COUNTIF(I12:I13,"Não Aderente")/COUNTA(I12:I13) -> 1
B12: Usuário possui detalhes da forma de tratamento dos dados | C12: =Controles!J29 -> Não aderente | D12: 0.16666667 | E12: Exigência | F12: Adesão | G12: =COUNTIF(F13:F13,"Não Aderente")/COUNTA(F13:F13) -> 1 | H12: Existência do programa | I12: =Controles!J111 -> Não aderente | J12: =COUNTIF(I12:I13,"Parcialmente Aderentemente Aderente")/COUNTA(I12:I13) -> 0
B13: Processo de resposta impresso/eletrônico | C13: =Controles!J30 -> Não aderente | E13: Existência do processo e documentação | F13: =Controles!J107 -> Não aderente | G13: =COUNTIF(F13:F13,"Parcialmente Aderente")/COUNTA(F13:F13) -> 0 | H13: Demonstração de efetividade | I13: =Controles!J118 -> Não aderente | J13: =COUNTIF(I12:I13,"N/A")/COUNTA(I12:I13) -> 0
B14: Existência de processo de resposta | C14: =Controles!J31 -> Não aderente | G14: =COUNTIF(F13:F13,"N/A")/COUNTA(F13:F13) -> 0
B15: O processo aciona todas as empresas com as quais os dados foram compartilhados | C15: =Controles!J32 -> Não aderente | E15: Privacy by Design | G15: =COUNTIF(F17:F18,"Aderente")/COUNTA(F17:F18) -> 0 | H15: Término do tratamento de dados | J15: =COUNTIF(I17:I18,"Aderente")/COUNTA(I17:I18) -> 0
B16: Existência de decisões baseadas em tratamentos automatizados | C16: =Controles!J33 -> Não aderente | E16: Exigência | F16: Adesão | G16: =COUNTIF(F17:F18,"Não Aderente")/COUNTA(F17:F18) -> 1 | H16: Exigência | I16: Adesão | J16: =COUNTIF(I17:I18,"Não Aderente")/COUNTA(I17:I18) -> 0
E17: Considera os 10 princípios da boa-fé | F17: =Controles!J22 -> Não aderente | G17: =COUNTIF(F17:F18,"Parcialmente Aderente")/COUNTA(F17:F18) -> 0 | H17: Existência de prazo de retenção | I17: =Controles!J71 -> 0 | J17: =COUNTIF(I17:I18,"Parcialmente Aderentemente Aderente")/COUNTA(I17:I18) -> 0
B18: Segurança da Informação | D18: 0 | E18: Processo documentado | F18: =Controles!J23 -> Não aderente | G18: =COUNTIF(F17:F18,"N/A")/COUNTA(F17:F18) -> 0 | H18: Existência de dados pessoais com prazo de retenção indeterminado | I18: =Controles!J77 -> 0 | J18: =COUNTIF(I17:I18,"N/A")/COUNTA(I17:I18) -> 0
B19: Exigência | C19: Adesão | D19: 0.6
B20: Dados armazenados em sistemas com controle de acesso/Revisão de acesso | C20: =Controles!J98 -> Aderente | D20: 0.4 | E20: Transferência internacional de dados | G20: =COUNTIF(F22:F22,"Aderente")/COUNTA(F22:F22) -> 0 | H20: Tratamento de Dados Pessoais - Compartilhamento de dados | J20: =COUNTIF(I22:I22,"Aderente")/COUNTA(I22:I22) -> 0
B21: Backup periódico de dados pessoais/PCN e DRP | C21: =Controles!J101 -> Parcialmente aderente | D21: 0 | E21: Exigência | F21: Adesão | G21: =COUNTIF(F22:F22,"Não Aderente")/COUNTA(F22:F22) -> 1 | H21: Exigência | I21: Adesão | J21: =COUNTIF(I22:I22,"Não Aderente")/COUNTA(I22:I22) -> 1
B22: Dados pessoais protegidos por técnicas e processos que previnem sua alteração e perda de integridade | C22: =Controles!J103 -> Não aderente | E22: Dados pessoais transferidos para outros países | F22: =Controles!J82 -> Não aderente | G22: =COUNTIF(F22:F22,"Parcialmente Aderente")/COUNTA(F22:F22) -> 0 | H22: Informação ao titular sobre compartilhamento de dados com outros controladores | I22: =Controles!J81 -> Não aderente | J22: =COUNTIF(I22:I22,"Parcialmente Aderentemente Aderente")/COUNTA(I22:I22) -> 0
B23: Dados pessoais protegidos por criptografia | C23: =Controles!J105 -> Não aderente | G23: =COUNTIF(F22:F22,"N/A")/COUNTA(F22:F22) -> 0 | J23: =COUNTIF(I22:I22,"N/A")/COUNTA(I22:I22) -> 0
B24: Processo que garante que o operador possua processos de segurança da informação | C24: =Controles!J106 -> Não aderente | E24: Tratamento de Dados Pessoais - Legitimação de uso de dados | G24: =COUNTIF(F26:F28,"Aderente")/COUNTA(F26:F28) -> 0 | H24: Tratamento de Dados Pessoais - Obtenção de Consentimento | J24: =COUNTIF(I26:I26,"Aderente")/COUNTA(I26:I26) -> 0
E25: Exigência | F25: Adesão | G25: =COUNTIF(F26:F28,"Não Aderente")/COUNTA(F26:F28) -> 0.33333333 | H25: Exigência | I25: Adesão | J25: =COUNTIF(I26:I26,"Não Aderente")/COUNTA(I26:I26) -> 0
B26: Tratamento de Dados Pessoais - Dados Públicos | D26: 0 | E26: Possui inventário de dados pessoais | F26: =Controles!J34 -> Parcialmente aderente | G26: =COUNTIF(F26:F28,"Parcialmente Aderente")/COUNTA(F26:F28) -> 0.33333333 | H26: Obtido de forma livre | I26: =Controles!J43 -> N/A | J26: =COUNTIF(I26:I26,"Parcialmente Aderentemente Aderente")/COUNTA(I26:I26) -> 0
B27: Exigência | C27: Adesão | D27: 1 | E27: Uso de legítimo interesse limitado | F27: =Controles!J36 -> 0 | G27: =COUNTIF(F26:F28,"N/A")/COUNTA(F26:F28) -> 0 | J27: =COUNTIF(I26:I26,"N/A")/COUNTA(I26:I26) -> 1
B28: Considera a finalidade, boa-fé e interesse público | C28: =Controles!J40 -> Parcialmente aderente | D28: 0 | E28: Documentação pelo controlador e operador | F28: =Controles!J39 -> Não aderente | H28: Tratamento de Dados Pessoais - Revogação de Consentimento | J28: =COUNTIF(I30:I30,"Aderente")/COUNTA(I30:I30) -> 0
D29: 0 | H29: Exigência | I29: Adesão | J29: =COUNTIF(I30:I30,"Não Aderente")/COUNTA(I30:I30) -> 0
E30: Tratamento de Dados Pessoais - Atualização de Consentimento | G30: =COUNTIF(F32:F32,"Aderente")/COUNTA(F32:F32) -> 0 | H30: Revogação a qualquer momento | I30: =Controles!J44 -> N/A | J30: =COUNTIF(I30:I30,"Parcialmente Aderentemente Aderente")/COUNTA(I30:I30) -> 0
B31: Tratamento de Dados Pessoais - Tratamento de dados obrigatório | E31: Exigência | F31: Adesão | G31: =COUNTIF(F32:F32,"Não Aderente")/COUNTA(F32:F32) -> 1 | J31: =COUNTIF(I30:I30,"N/A")/COUNTA(I30:I30) -> 1
B32: Exigência | C32: Adesão | D32: 0 | E32: Existência do processo | F32: =Controles!J45 -> Não aderente | G32: =COUNTIF(F32:F32,"Parcialmente Aderente")/COUNTA(F32:F32) -> 0 | H32: Tratamento de Dados Pessoais - Poder Públicos
B33: Condição obrigatória | C33: =Controles!J48 -> Parcialmente aderente | D33: 0 | G33: =COUNTIF(F32:F32,"N/A")/COUNTA(F32:F32) -> 0 | H33: Exigência | I33: Adesão | J33: =COUNTIF(I34:I41,"Aderente")/COUNTA(I34:I41) -> 0
D34: 1 | E34: Tratamento de Dados Pessoais Sensíveis - Sem Consentimento | G34: =COUNTIF(F36:F36,"Aderente")/COUNTA(F36:F36) -> 0 | H34: Dados coletados necessários | I34: =Controles!J119 -> N/A | J34: =COUNTIF(I34:I41,"Não Aderente")/COUNTA(I34:I41) -> 0
B35: Tratamento de Dados Pessoais Sensíveis - Anonimização | D35: 0 | E35: Exigência | F35: Adesão | G35: =COUNTIF(F36:F36,"Não Aderente")/COUNTA(F36:F36) -> 0 | H35: DPO nomeado por órgão público | I35: =Controles!J120 -> N/A | J35: =COUNTIF(I34:I41,"Parcialmente Aderentemente Aderente")/COUNTA(I34:I41) -> 0
B36: Exigência | C36: Adesão | D36: 0 | E36: Tratamento de dados sensíveis limitado às condições impostas | F36: =Controles!J52 -> 0 | G36: =COUNTIF(F36:F36,"Parcialmente Aderente")/COUNTA(F36:F36) -> 0 | H36: Formato interoperável e estruturado de dados | I36: =Controles!J121 -> N/A | J36: =COUNTIF(I34:I41,"N/A")/COUNTA(I34:I41) -> 1
B37: Dados sensíveis são anonimizados | C37: =Controles!J62 -> N/A | D37: 0 | G37: =COUNTIF(F36:F36,"N/A")/COUNTA(F36:F36) -> 0 | H37: Uso compartilhado de dados pessoais atende finalidades específicas | I37: =Controles!J122 -> N/A
D38: 1 | E38: Tratamento de Dados Pessoais Sensíveis - Compartilhamento entre controladores | G38: =COUNTIF(F40:F40,"Aderente")/COUNTA(F40:F40) -> 0 | H38: Transferência de dados para empresas privadas | I38: =Controles!J123 -> N/A
B39: Tratamento de Dados Pessoais Sensíveis - Consentimento | D39: 0 | E39: Exigência | F39: Adesão | G39: =COUNTIF(F40:F40,"Não Aderente")/COUNTA(F40:F40) -> 1 | H39: Contratos, convênios e instrumentos congêneres são comunicados à autoridade nacional | I39: =Controles!J124 -> N/A
B40: Exigência | C40: Adesão | D40: 1 | E40: Existe compartilhamento com outros controladores | F40: =Controles!J60 -> Não aderente | G40: =COUNTIF(F40:F40,"Parcialmente Aderente")/COUNTA(F40:F40) -> 0 | H40: Comunicação de dados pessoais de PJ de direito público à pessoa de direito privado é informado à autoridade nacional | I40: =Controles!J125 -> N/A
B41: Consentimento específico e destacado | C41: =Controles!J50 -> N/A | D41: 0 | G41: =COUNTIF(F40:F40,"N/A")/COUNTA(F40:F40) -> 0
D42: 0 | E42: Tratamento de Dados Pessoais Sensíveis - Estudos e Pesquisa de Saúde Pública | G42: =COUNTIF(F44:F44,"Aderente")/COUNTA(F44:F44) -> 0
B43: Tratamento de Dados Pessoais Sensíveis - Crianças e Adolescentes | D43: 0 | E43: Exigência | F43: Adesão | G43: =COUNTIF(F44:F44,"Não Aderente")/COUNTA(F44:F44) -> 0
B44: Exigência | C44: Adesão | D44: 0.66666667 | E44: Os dados são tratados para realizar a pesquisa | F44: =Controles!J65 -> N/A | G44: =COUNTIF(F44:F44,"Parcialmente Aderente")/COUNTA(F44:F44) -> 0
B45: Tratamento de dados mediante coleta de consentimento do responsável | C45: =Controles!J67 -> N/A | D45: 0 | G45: =COUNTIF(F44:F44,"N/A")/COUNTA(F44:F44) -> 1
B46: Direitos do titular em canal público | C46: =Controles!J68 -> N/A | D46: 0.33333333
B47: Não obrigatoriedade de dados pessoais para prestação de serviço/acesso | C47: =Controles!J69 -> N/A | G47: Tópico | H47: Andamento
B50: Aderência Total à LGPD
B51: =(COUNTIFS($C$7:$C$47,$C51)+COUNTIFS($F$7:$F$47,$C51)+COUNTIFS($I$7:$I$47,$C51))*100/50 -> 2 | C51: Aderente
B52: =(COUNTIFS($C$7:$C$47,$C52)+COUNTIFS($F$7:$F$47,$C52)+COUNTIFS($I$7:$I$47,$C52))*100/50 -> 50 | C52: Não Aderente
B53: =(COUNTIFS($C$7:$C$47,$C53)+COUNTIFS($F$7:$F$47,$C53)+COUNTIFS($I$7:$I$47,$C53))*100/50 -> 8 | C53: Parcialmente Aderente | E53: Finalizado | F53: =COUNTIFS(Controles!I7:I125,E53) -> 35
B54: =(COUNTIFS($C$7:$C$47,$C54)+COUNTIFS($F$7:$F$47,$C54)+COUNTIFS($I$7:$I$47,$C54))*100/50 -> 30 | C54: N/A | E54: Em andamento | F54: =COUNTIFS(Controles!I8:I126,E54) -> 25
E55: Não iniciado | F55: =COUNTIFS(Controles!I9:I127,E55) -> 52
B56: Mapeamento | E56: N/A | F56: =COUNTIFS(Controles!I10:I128,E56) -> 0
B57: Tópico | C57: Andamento
B58: Privacy By Design | C58: =COUNTIF(Controles!I7:I23,"Finalizado")/2*100+COUNTIF(Controles!I7:I23,"Em andamento")/2*50-COUNTIF(Controles!I7:I23,"Não inciado")/2*100 -> 325
B59: Direito dos titulares dos dados | C59: =COUNTIF(Controles!I28:I33,"Finalizado")/6*100+COUNTIF(Controles!I28:I33,"Em andamento")/6*50-COUNTIF(Controles!I28:I33,"Não inciado")/6*100 -> 0
B60: DPIA | C60: =(COUNTIF(Controles!I25:I26,"Finalizado")/3*100+COUNTIF(Controles!I25:I26,"Em andamento")/3*50-COUNTIF(Controles!I25:I26,"Não inciado")/3*100)+(COUNTIF(Controles!I27,"Finalizado")/3*100+COUNTIF(Controles!I27,"Em andamento")/3*50-COUNTIF(Controles!I27,"Não inciado")/3*100) -> 0
B61: Tratamento dos dados pessoais - Legitimação de uso de dados | C61: =COUNTIF(Controles!I34:I39,"Finalizado")/3*100+COUNTIF(Controles!I34:I39,"Em andamento")/3*50-COUNTIF(Controles!I34:I39,"Não inciado")/3*100 -> 50
B62: Tratamento dos dados pessoais - Dados públicos | C62: =COUNTIF(Controles!I41:I41,"Finalizado")/2*100+COUNTIF(Controles!I41:I41,"Em andamento")/2*50-COUNTIF(Controles!I41:I41,"Não inciado")/2*100 -> 0
B63: Tratamento dos dados pessoais - Compartilhamento de dados | C63: =COUNTIF(Controles!I42:I42,"Finalizado")/2*100+COUNTIF(Controles!I42:I42,"Em andamento")/2*50-COUNTIF(Controles!I42:I42,"Não inciado")/2*100 -> 50
B64: Tratamento dos dados pessoais - Obtenção do Consentimento | C64: =COUNTIF(Controles!I42,"Finalizado")*100+COUNTIF(Controles!I42,"Em andamento")*50-COUNTIF(Controles!I42,"Não inciado")*100 -> 100
B65: Tratamento dos dados pessoais - Revogação do Consentimento | C65: =COUNTIF(Controles!I44,"Finalizado")*100+COUNTIF(Controles!I44,"Em andamento")*50-COUNTIF(Controles!I44,"Não inciado")*100 -> 100
B66: Tratamento dos dados pessoais - Atualização do Consentimento | C66: =COUNTIF(Controles!I45,"Finalizado")*100+COUNTIF(Controles!I45,"Em andamento")*50-COUNTIF(Controles!I45,"Não inciado")*100 -> 0
B67: Tratamento dos dados pessoais - Tratamento de dados obrigatória | C67: =COUNTIF(Controles!I48:I49,"Finalizado")*100+COUNTIF(Controles!I48:I49,"Em andamento")*50-COUNTIF(Controles!I48:I49,"Não inciado")*100 -> 100
B68: Tratamento dos dados pessoais sensíveis - Consentimento | C68: =COUNTIF(Controles!I50,"Finalizado")*100+COUNTIF(Controles!I50,"Em andamento")*50-COUNTIF(Controles!I50,"Não inciado")*100 -> 100
B69: Tratamento dos dados pessoais sensíveis - Compartilhamento entre controladores | C69: =COUNTIF(Controles!I60,"Finalizado")*100+COUNTIF(Controles!I60,"Em andamento")*50-COUNTIF(Controles!I60,"Não inciado")*100 -> 0
B70: Tratamento dos dados pessoais sensíveis - Anonimização | C70: =COUNTIF(Controles!I62,"Finalizado")*100+COUNTIF(Controles!I62,"Em andamento")*50-COUNTIF(Controles!I62,"Não inciado")*100 -> 100
B71: Tratamento dos dados pessoais sensíveis - Estudos e pesquisas de saúde pública | C71: =COUNTIF(Controles!I65,"Finalizado")*100+COUNTIF(Controles!I65,"Em andamento")*50-COUNTIF(Controles!I65,"Não inciado")*100 -> 100
B72: Tratamento dos dados pessoais sensíveis - Sem consentimento | C72: =COUNTIF(Controles!I52,"Finalizado")*100+COUNTIF(Controles!I52,"Em andamento")*50-COUNTIF(Controles!I52,"Não inciado")*100 -> 0
B73: Tratamento dos dados pessoais sensíveis - Crianças e adolescentes | C73: =COUNTIF(Controles!I67:I69,"Finalizado")/3*100+COUNTIF(Controles!I67:I69,"Em andamento")/3*50-COUNTIF(Controles!I67:I69,"Não inciado")/3*100 -> 100
B74: Término do Tratamento de Dados | C74: =COUNTIF(Controles!I71:I77,"Finalizado")/2*100+COUNTIF(Controles!I71:I77,"Em andamento")/2*50-COUNTIF(Controles!I71:I77,"Não inciado")/2*100 -> 0
B75: Transferência internacional de dados | C75: =COUNTIF(Controles!I82,"Finalizado")*100+COUNTIF(Controles!I82,"Em andamento")*50-COUNTIF(Controles!I82,"Não inciado")*100 -> 50
B76: Agentes de tratamento de dados | C76: =COUNTIF(Controles!I93,"Finalizado")*100+COUNTIF(Controles!I93,"Em andamento")*50-COUNTIF(Controles!I93,"Não inciado")*100 -> 0
B77: DPO | C77: =COUNTIF(Controles!I95:I97,"Finalizado")/2*100+COUNTIF(Controles!I95:I97,"Em andamento")/2*50-COUNTIF(Controles!I95:I97,"Não inciado")/2*100 -> 50
B78: Segurança da Informação | C78: =COUNTIF(Controles!I98:I106,"Finalizado")/5*100+COUNTIF(Controles!I98:I106,"Em andamento")/5*50-COUNTIF(Controles!I98:I106,"Não inciado")/5*100 -> 40
B79: Gestão de Incidentes de Privacidade | C79: =COUNTIF(Controles!I107,"Finalizado")*100+COUNTIF(Controles!I107,"Em andamento")*50-COUNTIF(Controles!I107,"Não inciado")*100 -> 0
B80: Programa de Governança em Privacidade | C80: =COUNTIF(Controles!I111:I118,"Finalizado")/2*100+COUNTIF(Controles!I111:I118,"Em andamento")/2*50-COUNTIF(Controles!I111:I118,"Não inciado")/2*100 -> 0
B81: Tratamento de dados pessoais - poder público | C81: =COUNTIF(Controles!I119:I125,"Finalizado")/7*100+COUNTIF(Controles!I119:I125,"Em andamento")/7*50-COUNTIF(Controles!I119:I125,"Não inciado")/7*100 -> 100

Sheet Status da Análise
